[
  {
    "domainId": 1,
    "domainTitle": "कोयला",
    "domainSubtitle": "ज्वलनशील चट्टान।",
    "domainThumbnail": "images/domain_1.webp",
    "branchId": 1,
    "branchTitle": "भूगर्भशास्त्र",
    "branchSubtitle": "पृथ्वी का अध्ययन",
    "branchThumbnail": "images/branch_1.webp",
    "branchHref": "https://www.miracles-of-quran.com/geology.html",
    "domainHref": "https://www.miracles-of-quran.com/coal.html",
    "difficultyLevel": "आसान"
  },
  {
    "domainId": 2,
    "domainTitle": "मरुस्थलीकरण",
    "domainSubtitle": "नदियाँ रेगिस्तान में बदल जाती हैं।",
    "domainThumbnail": "images/domain_2.webp",
    "branchId": 7,
    "branchTitle": "अंतरिक्ष-विज्ञान",
    "branchSubtitle": "वातावरण का अध्ययन",
    "branchThumbnail": "images/branch_7.webp",
    "branchHref": "https://www.miracles-of-quran.com/meteorology.html",
    "domainHref": "https://www.miracles-of-quran.com/desertification.html",
    "difficultyLevel": "मध्यम"
  },
  {
    "domainId": 3,
    "domainTitle": "भूस्खलन",
    "domainSubtitle": "भूमि का विस्थापन।",
    "domainThumbnail": "images/domain_3.webp",
    "branchId": 1,
    "branchTitle": "भूगर्भशास्त्र",
    "branchSubtitle": "पृथ्वी का अध्ययन",
    "branchThumbnail": "images/branch_1.webp",
    "branchHref": "https://www.miracles-of-quran.com/geology.html",
    "domainHref": "https://www.miracles-of-quran.com/landslides.html",
    "difficultyLevel": "आसान"
  },
  {
    "domainId": 4,
    "domainTitle": "अपक्षय एवं अपरदन",
    "domainSubtitle": "चट्टानों को चिकना करता है।",
    "domainThumbnail": "images/domain_4.webp",
    "branchId": 14,
    "branchTitle": "जल विज्ञान",
    "branchSubtitle": "पृथ्वी के तरल पदार्थों का अध्ययन",
    "branchThumbnail": "images/branch_14.webp",
    "branchHref": "https://www.miracles-of-quran.com/hydrology.html",
    "domainHref": "https://www.miracles-of-quran.com/weathering_erosion.html",
    "difficultyLevel": "उन्नत"
  },
  {
    "domainId": 5,
    "domainTitle": "झरझरा चट्टानें",
    "domainSubtitle": "पानी स्टोर कर सकते हैं।",
    "domainThumbnail": "images/domain_5.webp",
    "branchId": 14,
    "branchTitle": "जल विज्ञान",
    "branchSubtitle": "पृथ्वी के तरल पदार्थों का अध्ययन",
    "branchThumbnail": "images/branch_14.webp",
    "branchHref": "https://www.miracles-of-quran.com/hydrology.html",
    "domainHref": "https://www.miracles-of-quran.com/porous_rocks.html",
    "difficultyLevel": "उन्नत"
  },
  {
    "domainId": 6,
    "domainTitle": "पहाड़ों",
    "domainSubtitle": "जड़ें हों।",
    "domainThumbnail": "images/domain_6.webp",
    "branchId": 1,
    "branchTitle": "भूगर्भशास्त्र",
    "branchSubtitle": "पृथ्वी का अध्ययन",
    "branchThumbnail": "images/branch_1.webp",
    "branchHref": "https://www.miracles-of-quran.com/geology.html",
    "domainHref": "https://www.miracles-of-quran.com/mountains.html",
    "difficultyLevel": "उन्नत"
  },
  {
    "domainId": 7,
    "domainTitle": "आंतरिक तरंगें",
    "domainSubtitle": "समुद्रों में आंतरिक तरंगें होती हैं।",
    "domainThumbnail": "images/domain_7.webp",
    "branchId": 14,
    "branchTitle": "जल विज्ञान",
    "branchSubtitle": "पृथ्वी के तरल पदार्थों का अध्ययन",
    "branchThumbnail": "images/branch_14.webp",
    "branchHref": "https://www.miracles-of-quran.com/hydrology.html",
    "domainHref": "https://www.miracles-of-quran.com/internal_waves.html",
    "difficultyLevel": "चरम"
  },
  {
    "domainId": 8,
    "domainTitle": "धरती",
    "domainSubtitle": "घूमता हुआ गोला।",
    "domainThumbnail": "images/domain_8.webp",
    "branchId": 1,
    "branchTitle": "भूगर्भशास्त्र",
    "branchSubtitle": "पृथ्वी का अध्ययन",
    "branchThumbnail": "images/branch_1.webp",
    "branchHref": "https://www.miracles-of-quran.com/geology.html",
    "domainHref": "https://www.miracles-of-quran.com/earth.html",
    "difficultyLevel": "आसान"
  },
  {
    "domainId": 9,
    "domainTitle": "झांवां",
    "domainSubtitle": "पृथ्वी पर सबसे कम घना पत्थर।",
    "domainThumbnail": "images/domain_9.webp",
    "branchId": 1,
    "branchTitle": "भूगर्भशास्त्र",
    "branchSubtitle": "पृथ्वी का अध्ययन",
    "branchThumbnail": "images/branch_1.webp",
    "branchHref": "https://www.miracles-of-quran.com/geology.html",
    "domainHref": "https://www.miracles-of-quran.com/pumice.html",
    "difficultyLevel": "आसान"
  },
  {
    "domainId": 10,
    "domainTitle": "फोटो जोन",
    "domainSubtitle": "दृश्य प्रकाश के साथ महासागर खंड।",
    "domainThumbnail": "images/domain_10.webp",
    "branchId": 14,
    "branchTitle": "जल विज्ञान",
    "branchSubtitle": "पृथ्वी के तरल पदार्थों का अध्ययन",
    "branchThumbnail": "images/branch_14.webp",
    "branchHref": "https://www.miracles-of-quran.com/hydrology.html",
    "domainHref": "https://www.miracles-of-quran.com/photic_zone.html",
    "difficultyLevel": "उन्नत"
  },
  {
    "domainId": 11,
    "domainTitle": "आर्किटेक्चर",
    "domainSubtitle": "पहाड़ हिलते हैं।",
    "domainThumbnail": "images/domain_11.webp",
    "branchId": 1,
    "branchTitle": "भूगर्भशास्त्र",
    "branchSubtitle": "पृथ्वी का अध्ययन",
    "branchThumbnail": "images/branch_1.webp",
    "branchHref": "https://www.miracles-of-quran.com/geology.html",
    "domainHref": "https://www.miracles-of-quran.com/tectonics.html",
    "difficultyLevel": "उन्नत"
  },
  {
    "domainId": 12,
    "domainTitle": "मृत सागर",
    "domainSubtitle": "पृथ्वी पर सबसे निचला बिंदु।",
    "domainThumbnail": "images/domain_12.webp",
    "branchId": 14,
    "branchTitle": "जल विज्ञान",
    "branchSubtitle": "पृथ्वी के तरल पदार्थों का अध्ययन",
    "branchThumbnail": "images/branch_14.webp",
    "branchHref": "https://www.miracles-of-quran.com/hydrology.html",
    "domainHref": "https://www.miracles-of-quran.com/dead_sea.html",
    "difficultyLevel": "आसान"
  },
  {
    "domainId": 13,
    "domainTitle": "सिंकहोल",
    "domainSubtitle": "प्राकृतिक अवसाद या जमीन में छेद।",
    "domainThumbnail": "images/domain_13.webp",
    "branchId": 1,
    "branchTitle": "भूगर्भशास्त्र",
    "branchSubtitle": "पृथ्वी का अध्ययन",
    "branchThumbnail": "images/branch_1.webp",
    "branchHref": "https://www.miracles-of-quran.com/geology.html",
    "domainHref": "https://www.miracles-of-quran.com/sinkhole.html",
    "difficultyLevel": "मध्यम"
  },
  {
    "domainId": 14,
    "domainTitle": "ज्वालामुखी",
    "domainSubtitle": "भूकंप या झटके विस्फोट से पहले होते हैं।",
    "domainThumbnail": "images/domain_14.webp",
    "branchId": 1,
    "branchTitle": "भूगर्भशास्त्र",
    "branchSubtitle": "पृथ्वी का अध्ययन",
    "branchThumbnail": "images/branch_1.webp",
    "branchHref": "https://www.miracles-of-quran.com/geology.html",
    "domainHref": "https://www.miracles-of-quran.com/volcano.html",
    "difficultyLevel": "आसान"
  },
  {
    "domainId": 15,
    "domainTitle": "झटकों",
    "domainSubtitle": "विलंबित कमजोर भूकंप।",
    "domainThumbnail": "images/domain_15.webp",
    "branchId": 1,
    "branchTitle": "भूगर्भशास्त्र",
    "branchSubtitle": "पृथ्वी का अध्ययन",
    "branchThumbnail": "images/branch_1.webp",
    "branchHref": "https://www.miracles-of-quran.com/geology.html",
    "domainHref": "https://www.miracles-of-quran.com/aftershocks.html",
    "difficultyLevel": "आसान"
  },
  {
    "domainId": 16,
    "domainTitle": "खनिज पदार्थ",
    "domainSubtitle": "अलग-अलग रंग हों।",
    "domainThumbnail": "images/domain_16.webp",
    "branchId": 1,
    "branchTitle": "भूगर्भशास्त्र",
    "branchSubtitle": "पृथ्वी का अध्ययन",
    "branchThumbnail": "images/branch_1.webp",
    "branchHref": "https://www.miracles-of-quran.com/geology.html",
    "domainHref": "https://www.miracles-of-quran.com/minerals.html",
    "difficultyLevel": "आसान"
  },
  {
    "domainId": 17,
    "domainTitle": "जल उष्मा",
    "domainSubtitle": "गहरे भूमिगत से गर्म पानी।",
    "domainThumbnail": "images/domain_17.webp",
    "branchId": 14,
    "branchTitle": "जल विज्ञान",
    "branchSubtitle": "पृथ्वी के तरल पदार्थों का अध्ययन",
    "branchThumbnail": "images/branch_14.webp",
    "branchHref": "https://www.miracles-of-quran.com/hydrology.html",
    "domainHref": "https://www.miracles-of-quran.com/hydrothermal.html",
    "difficultyLevel": "उन्नत"
  },
  {
    "domainId": 18,
    "domainTitle": "पाला अपक्षय",
    "domainSubtitle": "पानी चट्टानों को तोड़ देता है।",
    "domainThumbnail": "images/domain_18.webp",
    "branchId": 1,
    "branchTitle": "अंतरिक्ष-विज्ञान",
    "branchSubtitle": "वातावरण का अध्ययन",
    "branchThumbnail": "images/branch_7.webp",
    "branchHref": "https://www.miracles-of-quran.com/meteorology.html",
    "domainHref": "https://www.miracles-of-quran.com/frost_weathering.html",
    "difficultyLevel": "उन्नत"
  },
  {
    "domainId": 19,
    "domainTitle": "सबडक्शन",
    "domainSubtitle": "प्लेटों का डूबना।",
    "domainThumbnail": "images/domain_19.webp",
    "branchId": 1,
    "branchTitle": "भूगर्भशास्त्र",
    "branchSubtitle": "पृथ्वी का अध्ययन",
    "branchThumbnail": "images/branch_1.webp",
    "branchHref": "https://www.miracles-of-quran.com/geology.html",
    "domainHref": "https://www.miracles-of-quran.com/subduction.html",
    "difficultyLevel": "चरम"
  },
  {
    "domainId": 20,
    "domainTitle": "गलत लाइनें",
    "domainSubtitle": "पृथ्वी में दरारें और दोष।",
    "domainThumbnail": "images/domain_20.webp",
    "branchId": 1,
    "branchTitle": "भूगर्भशास्त्र",
    "branchSubtitle": "पृथ्वी का अध्ययन",
    "branchThumbnail": "images/branch_1.webp",
    "branchHref": "https://www.miracles-of-quran.com/geology.html",
    "domainHref": "https://www.miracles-of-quran.com/fault_lines.html",
    "difficultyLevel": "चरम"
  },
  {
    "domainId": 21,
    "domainTitle": "भूकंप",
    "domainSubtitle": "भूमि का विस्थापन।",
    "domainThumbnail": "images/domain_21.webp",
    "branchId": 1,
    "branchTitle": "भूगर्भशास्त्र",
    "branchSubtitle": "पृथ्वी का अध्ययन",
    "branchThumbnail": "images/branch_1.webp",
    "branchHref": "https://www.miracles-of-quran.com/geology.html",
    "domainHref": "https://www.miracles-of-quran.com/earthquake.html",
    "difficultyLevel": "आसान"
  },
  {
    "domainId": 22,
    "domainTitle": "मिट्टी का विस्तार",
    "domainSubtitle": "गड्ढों का कारण बनता है।",
    "domainThumbnail": "images/domain_22.webp",
    "branchId": 1,
    "branchTitle": "भूगर्भशास्त्र",
    "branchSubtitle": "पृथ्वी का अध्ययन",
    "branchThumbnail": "images/branch_1.webp",
    "branchHref": "https://www.miracles-of-quran.com/geology.html",
    "domainHref": "https://www.miracles-of-quran.com/soil_expansion.html",
    "difficultyLevel": "उन्नत"
  },
  {
    "domainId": 23,
    "domainTitle": "आंतरिक पर्वत",
    "domainSubtitle": "सतह से 400 किमी नीचे।",
    "domainThumbnail": "images/domain_23.webp",
    "branchId": 1,
    "branchTitle": "भूगर्भशास्त्र",
    "branchSubtitle": "पृथ्वी का अध्ययन",
    "branchThumbnail": "images/branch_1.webp",
    "branchHref": "https://www.miracles-of-quran.com/geology.html",
    "domainHref": "https://www.miracles-of-quran.com/internal_mountains.html",
    "difficultyLevel": "चरम"
  },
  {
    "domainId": 24,
    "domainTitle": "एस्थेनोस्फीयर",
    "domainSubtitle": "पिघला हुआ परत।",
    "domainThumbnail": "images/domain_24.webp",
    "branchId": 14,
    "branchTitle": "जल विज्ञान",
    "branchSubtitle": "पृथ्वी के तरल पदार्थों का अध्ययन",
    "branchThumbnail": "images/branch_14.webp",
    "branchHref": "https://www.miracles-of-quran.com/hydrology.html",
    "domainHref": "https://www.miracles-of-quran.com/asthenosphere.html",
    "difficultyLevel": "चरम"
  },
  {
    "domainId": 25,
    "domainTitle": "पाइरिटाइज़्ड जीवाश्म",
    "domainSubtitle": "जीवाश्म मूर्ख का सोना।",
    "domainThumbnail": "images/domain_25.webp",
    "branchId": 8,
    "branchTitle": "रसायन शास्त्र",
    "branchSubtitle": "तत्वों और यौगिकों का विज्ञान",
    "branchThumbnail": "images/branch_8.webp",
    "branchHref": "https://www.miracles-of-quran.com/chemistry.html",
    "domainHref": "https://www.miracles-of-quran.com/pyritized_fossils.html",
    "difficultyLevel": "उन्नत"
  },
  {
    "domainId": 26,
    "domainTitle": "पढ़ना",
    "domainSubtitle": "नवजात दिमाग पढ़ने के लिए तैयार है।",
    "domainThumbnail": "images/domain_26.webp",
    "branchId": 2,
    "branchTitle": "जीवविज्ञान",
    "branchSubtitle": "जीवों का विज्ञान",
    "branchThumbnail": "images/branch_2.jpeg",
    "branchHref": "https://www.miracles-of-quran.com/biology.html",
    "domainHref": "https://www.miracles-of-quran.com/reading.html",
    "difficultyLevel": "चरम"
  },
  {
    "domainId": 27,
    "domainTitle": "डर",
    "domainSubtitle": "दिल से जुड़ा हुआ।",
    "domainThumbnail": "images/domain_27.webp",
    "branchId": 2,
    "branchTitle": "जीवविज्ञान",
    "branchSubtitle": "जीवों का विज्ञान",
    "branchThumbnail": "images/branch_2.jpeg",
    "branchHref": "https://www.miracles-of-quran.com/biology.html",
    "domainHref": "https://www.miracles-of-quran.com/fear.html",
    "difficultyLevel": "चरम"
  },
  {
    "domainId": 28,
    "domainTitle": "बहिःकंकाल",
    "domainSubtitle": "लीफ-कटर चींटियों को क्रिस्टल के साथ लेपित किया जाता है।",
    "domainThumbnail": "images/domain_28.webp",
    "branchId": 2,
    "branchTitle": "जीवविज्ञान",
    "branchSubtitle": "जीवों का विज्ञान",
    "branchThumbnail": "images/branch_2.jpeg",
    "branchHref": "https://www.miracles-of-quran.com/biology.html",
    "domainHref": "https://www.miracles-of-quran.com/exoskeleton.html",
    "difficultyLevel": "चरम"
  },
  {
    "domainId": 29,
    "domainTitle": "पुरुष प्रजनन क्षमता",
    "domainSubtitle": "हड्डियों से जुड़ा हुआ।",
    "domainThumbnail": "images/domain_29.webp",
    "branchId": 2,
    "branchTitle": "जीवविज्ञान",
    "branchSubtitle": "जीवों का विज्ञान",
    "branchThumbnail": "images/branch_2.jpeg",
    "branchHref": "https://www.miracles-of-quran.com/biology.html",
    "domainHref": "https://www.miracles-of-quran.com/male_fertility.html",
    "difficultyLevel": "उन्नत"
  },
  {
    "domainId": 30,
    "domainTitle": "स्तनपान",
    "domainSubtitle": "सामाजिक जुड़ाव।",
    "domainThumbnail": "images/domain_30.webp",
    "branchId": 2,
    "branchTitle": "जीवविज्ञान",
    "branchSubtitle": "जीवों का विज्ञान",
    "branchThumbnail": "images/branch_2.jpeg",
    "branchHref": "https://www.miracles-of-quran.com/biology.html",
    "domainHref": "https://www.miracles-of-quran.com/breastfeeding.html",
    "difficultyLevel": "आसान"
  },
  {
    "domainId": 31,
    "domainTitle": "कान का परदा",
    "domainSubtitle": "टूटना सुनवाई हानि का कारण बनता है।",
    "domainThumbnail": "images/domain_31.webp",
    "branchId": 15,
    "branchTitle": "शरीर क्रिया विज्ञान",
    "branchSubtitle": "अंगों के कार्य",
    "branchThumbnail": "images/branch_15.webp",
    "branchHref": "https://www.miracles-of-quran.com/physiology.html",
    "domainHref": "https://www.miracles-of-quran.com/eardrum.html",
    "difficultyLevel": "मध्यम"
  },
  {
    "domainId": 32,
    "domainTitle": "केरानोपारालिसिस",
    "domainSubtitle": "बिजली गिरने से हुआ।",
    "domainThumbnail": "images/domain_32.webp",
    "branchId": 2,
    "branchTitle": "जीवविज्ञान",
    "branchSubtitle": "जीवों का विज्ञान",
    "branchThumbnail": "images/branch_2.jpeg",
    "branchHref": "https://www.miracles-of-quran.com/biology.html",
    "domainHref": "https://www.miracles-of-quran.com/keraunoparalysis.html",
    "difficultyLevel": "चरम"
  },
  {
    "domainId": 33,
    "domainTitle": "अंदरुनी कान",
    "domainSubtitle": "संतुलन के लिए जिम्मेदार।",
    "domainThumbnail": "images/domain_33.webp",
    "branchId": 15,
    "branchTitle": "शरीर क्रिया विज्ञान",
    "branchSubtitle": "अंगों के कार्य",
    "branchThumbnail": "images/branch_15.webp",
    "branchHref": "https://www.miracles-of-quran.com/physiology.html",
    "domainHref": "https://www.miracles-of-quran.com/inner_ear.html",
    "difficultyLevel": "आसान"
  },
  {
    "domainId": 34,
    "domainTitle": "मोतियाबिंद",
    "domainSubtitle": "अवसाद से जुड़ा हुआ।",
    "domainThumbnail": "images/domain_34.webp",
    "branchId": 15,
    "branchTitle": "शरीर क्रिया विज्ञान",
    "branchSubtitle": "अंगों के कार्य",
    "branchThumbnail": "images/branch_15.webp",
    "branchHref": "https://www.miracles-of-quran.com/physiology.html",
    "domainHref": "https://www.miracles-of-quran.com/cataracts.html",
    "difficultyLevel": "मध्यम"
  },
  {
    "domainId": 35,
    "domainTitle": "नज़र",
    "domainSubtitle": "अंतरिक्ष यात्री धुंधली दृष्टि का अनुभव करते हैं।",
    "domainThumbnail": "images/domain_35.webp",
    "branchId": 15,
    "branchTitle": "शरीर क्रिया विज्ञान",
    "branchSubtitle": "अंगों के कार्य",
    "branchThumbnail": "images/branch_15.webp",
    "branchHref": "https://www.miracles-of-quran.com/physiology.html",
    "domainHref": "https://www.miracles-of-quran.com/vision.html",
    "difficultyLevel": "उन्नत"
  },
  {
    "domainId": 36,
    "domainTitle": "हड्डियाँ",
    "domainSubtitle": "मांसपेशियों से पहले फार्म।",
    "domainThumbnail": "images/domain_36.webp",
    "branchId": 2,
    "branchTitle": "जीवविज्ञान",
    "branchSubtitle": "जीवों का विज्ञान",
    "branchThumbnail": "images/branch_2.jpeg",
    "branchHref": "https://www.miracles-of-quran.com/biology.html",
    "domainHref": "https://www.miracles-of-quran.com/bones.html",
    "difficultyLevel": "उन्नत"
  },
  {
    "domainId": 37,
    "domainTitle": "दूध",
    "domainSubtitle": "पोषक तत्व रक्त प्रवाह से आते हैं।",
    "domainThumbnail": "images/domain_37.webp",
    "branchId": 15,
    "branchTitle": "शरीर क्रिया विज्ञान",
    "branchSubtitle": "अंगों के कार्य",
    "branchThumbnail": "images/branch_15.webp",
    "branchHref": "https://www.miracles-of-quran.com/physiology.html",
    "domainHref": "https://www.miracles-of-quran.com/milk.html",
    "difficultyLevel": "आसान"
  },
  {
    "domainId": 38,
    "domainTitle": "अर्धसूत्रीविभाजन",
    "domainSubtitle": "कोशिका विभाजन।",
    "domainThumbnail": "images/domain_38.webp",
    "branchId": 2,
    "branchTitle": "जीवविज्ञान",
    "branchSubtitle": "जीवों का विज्ञान",
    "branchThumbnail": "images/branch_2.jpeg",
    "branchHref": "https://www.miracles-of-quran.com/biology.html",
    "domainHref": "https://www.miracles-of-quran.com/meiosis.html",
    "difficultyLevel": "उन्नत"
  },
  {
    "domainId": 39,
    "domainTitle": "शहद",
    "domainSubtitle": "प्राकृतिक एंटीबायोटिक।",
    "domainThumbnail": "images/domain_39.webp",
    "branchId": 2,
    "branchTitle": "जीवविज्ञान",
    "branchSubtitle": "जीवों का विज्ञान",
    "branchThumbnail": "images/branch_2.jpeg",
    "branchHref": "https://www.miracles-of-quran.com/biology.html",
    "domainHref": "https://www.miracles-of-quran.com/honey.html",
    "difficultyLevel": "आसान"
  },
  {
    "domainId": 40,
    "domainTitle": "बिस्तर घावों",
    "domainSubtitle": "बढ़े हुए दबाव के कारण हुआ।",
    "domainThumbnail": "images/domain_40.webp",
    "branchId": 15,
    "branchTitle": "शरीर क्रिया विज्ञान",
    "branchSubtitle": "अंगों के कार्य",
    "branchThumbnail": "images/branch_15.webp",
    "branchHref": "https://www.miracles-of-quran.com/physiology.html",
    "domainHref": "https://www.miracles-of-quran.com/bedsores.html",
    "difficultyLevel": "उन्नत"
  },
  {
    "domainId": 41,
    "domainTitle": "वसा",
    "domainSubtitle": "ऊर्जा का सबसे धीमा स्रोत।",
    "domainThumbnail": "images/domain_41.webp",
    "branchId": 2,
    "branchTitle": "जीवविज्ञान",
    "branchSubtitle": "जीवों का विज्ञान",
    "branchThumbnail": "images/branch_2.jpeg",
    "branchHref": "https://www.miracles-of-quran.com/biology.html",
    "domainHref": "https://www.miracles-of-quran.com/fats.html",
    "difficultyLevel": "आसान"
  },
  {
    "domainId": 42,
    "domainTitle": "जीवाणु",
    "domainSubtitle": "सूक्ष्म जीव।",
    "domainThumbnail": "images/domain_42.webp",
    "branchId": 2,
    "branchTitle": "जीवविज्ञान",
    "branchSubtitle": "जीवों का विज्ञान",
    "branchThumbnail": "images/branch_2.jpeg",
    "branchHref": "https://www.miracles-of-quran.com/biology.html",
    "domainHref": "https://www.miracles-of-quran.com/bacteria.html",
    "difficultyLevel": "चरम"
  },
  {
    "domainId": 44,
    "domainTitle": "कोलेस्ट्रॉल",
    "domainSubtitle": "धमनियों को बंद कर देता है।",
    "domainThumbnail": "images/domain_44.webp",
    "branchId": 15,
    "branchTitle": "शरीर क्रिया विज्ञान",
    "branchSubtitle": "अंगों के कार्य",
    "branchThumbnail": "images/branch_15.webp",
    "branchHref": "https://www.miracles-of-quran.com/physiology.html",
    "domainHref": "https://www.miracles-of-quran.com/cholesterol.html",
    "difficultyLevel": "उन्नत"
  },
  {
    "domainId": 45,
    "domainTitle": "सफेद बाल",
    "domainSubtitle": "सदमे से जुड़ा हुआ है।",
    "domainThumbnail": "images/domain_45.webp",
    "branchId": 2,
    "branchTitle": "जीवविज्ञान",
    "branchSubtitle": "जीवों का विज्ञान",
    "branchThumbnail": "images/branch_2.jpeg",
    "branchHref": "https://www.miracles-of-quran.com/biology.html",
    "domainHref": "https://www.miracles-of-quran.com/white_hair.html",
    "difficultyLevel": "आसान"
  },
  {
    "domainId": 46,
    "domainTitle": "हाइपोक्सिया",
    "domainSubtitle": "औक्सीजन की कमी।",
    "domainThumbnail": "images/domain_46.webp",
    "branchId": 15,
    "branchTitle": "शरीर क्रिया विज्ञान",
    "branchSubtitle": "अंगों के कार्य",
    "branchThumbnail": "images/branch_15.webp",
    "branchHref": "https://www.miracles-of-quran.com/physiology.html",
    "domainHref": "https://www.miracles-of-quran.com/hypoxia.html",
    "difficultyLevel": "चरम"
  },
  {
    "domainId": 47,
    "domainTitle": "मस्तिष्क कार्य",
    "domainSubtitle": "ललाट भाग झूठ को संभालता है।",
    "domainThumbnail": "images/domain_47.webp",
    "branchId": 15,
    "branchTitle": "शरीर क्रिया विज्ञान",
    "branchSubtitle": "अंगों के कार्य",
    "branchThumbnail": "images/branch_15.webp",
    "branchHref": "https://www.miracles-of-quran.com/physiology.html",
    "domainHref": "https://www.miracles-of-quran.com/brain_functions.html",
    "difficultyLevel": "उन्नत"
  },
  {
    "domainId": 48,
    "domainTitle": "विकास",
    "domainSubtitle": "भगवान ने विकास किया।",
    "domainThumbnail": "images/domain_48.webp",
    "branchId": 2,
    "branchTitle": "जीवविज्ञान",
    "branchSubtitle": "जीवों का विज्ञान",
    "branchThumbnail": "images/branch_2.jpeg",
    "branchHref": "https://www.miracles-of-quran.com/biology.html",
    "domainHref": "https://www.miracles-of-quran.com/evolution.html",
    "difficultyLevel": "चरम"
  },
  {
    "domainId": 49,
    "domainTitle": "शिष्य",
    "domainSubtitle": "झूठ बोलने पर फैलता है।",
    "domainThumbnail": "images/domain_49.webp",
    "branchId": 15,
    "branchTitle": "शरीर क्रिया विज्ञान",
    "branchSubtitle": "अंगों के कार्य",
    "branchThumbnail": "images/branch_15.webp",
    "branchHref": "https://www.miracles-of-quran.com/physiology.html",
    "domainHref": "https://www.miracles-of-quran.com/pupil.html",
    "difficultyLevel": "चरम"
  },
  {
    "domainId": 50,
    "domainTitle": "उंगलियों के निशान",
    "domainSubtitle": "प्रत्येक व्यक्ति के लिए अद्वितीय।",
    "domainThumbnail": "images/domain_50.webp",
    "branchId": 15,
    "branchTitle": "शरीर क्रिया विज्ञान",
    "branchSubtitle": "अंगों के कार्य",
    "branchThumbnail": "images/branch_15.webp",
    "branchHref": "https://www.miracles-of-quran.com/physiology.html",
    "domainHref": "https://www.miracles-of-quran.com/fingerprints.html",
    "difficultyLevel": "आसान"
  },
  {
    "domainId": 51,
    "domainTitle": "त्वचा की नसें",
    "domainSubtitle": "बाहरी त्वचा से जलन महसूस होना।",
    "domainThumbnail": "images/domain_51.webp",
    "branchId": 15,
    "branchTitle": "शरीर क्रिया विज्ञान",
    "branchSubtitle": "अंगों के कार्य",
    "branchThumbnail": "images/branch_15.webp",
    "branchHref": "https://www.miracles-of-quran.com/physiology.html",
    "domainHref": "https://www.miracles-of-quran.com/skin_nerves.html",
    "difficultyLevel": "मध्यम"
  },
  {
    "domainId": 52,
    "domainTitle": "उपवास",
    "domainSubtitle": "चिकित्सा लाभ है।",
    "domainThumbnail": "images/domain_52.webp",
    "branchId": 2,
    "branchTitle": "जीवविज्ञान",
    "branchSubtitle": "जीवों का विज्ञान",
    "branchThumbnail": "images/branch_2.jpeg",
    "branchHref": "https://www.miracles-of-quran.com/biology.html",
    "domainHref": "https://www.miracles-of-quran.com/fasting.html",
    "difficultyLevel": "उन्नत"
  },
  {
    "domainId": 53,
    "domainTitle": "चुंबकत्व",
    "domainSubtitle": "पृथ्वी के चुंबकीय क्षेत्र को सेंस करें।",
    "domainThumbnail": "images/domain_53.webp",
    "branchId": 2,
    "branchTitle": "जीवविज्ञान",
    "branchSubtitle": "जीवों का विज्ञान",
    "branchThumbnail": "images/branch_2.jpeg",
    "branchHref": "https://www.miracles-of-quran.com/biology.html",
    "domainHref": "https://www.miracles-of-quran.com/magnetoreception.html",
    "difficultyLevel": "चरम"
  },
  {
    "domainId": 54,
    "domainTitle": "अल्जाइमर",
    "domainSubtitle": "वृद्धावस्था से जुड़ा हुआ।",
    "domainThumbnail": "images/domain_54.webp",
    "branchId": 2,
    "branchTitle": "जीवविज्ञान",
    "branchSubtitle": "जीवों का विज्ञान",
    "branchThumbnail": "images/branch_2.jpeg",
    "branchHref": "https://www.miracles-of-quran.com/biology.html",
    "domainHref": "https://www.miracles-of-quran.com/alzheimer.html",
    "difficultyLevel": "मध्यम"
  },
  {
    "domainId": 55,
    "domainTitle": "काम",
    "domainSubtitle": "बल बार विस्थापन।",
    "domainThumbnail": "images/domain_55.webp",
    "branchId": 3,
    "branchTitle": "भौतिक विज्ञान",
    "branchSubtitle": "अंतरिक्ष और समय के माध्यम से गति और व्यवहार का विज्ञान",
    "branchThumbnail": "images/branch_3.webp",
    "branchHref": "https://www.miracles-of-quran.com/physics.html",
    "domainHref": "https://www.miracles-of-quran.com/work.html",
    "difficultyLevel": "आसान"
  },
  {
    "domainId": 56,
    "domainTitle": "प्रकाश कि गति",
    "domainSubtitle": "12000 चंद्र परिक्रमा/पृथ्वी दिवस।",
    "domainThumbnail": "images/domain_56.webp",
    "branchId": 3,
    "branchTitle": "भौतिक विज्ञान",
    "branchSubtitle": "अंतरिक्ष और समय के माध्यम से गति और व्यवहार का विज्ञान",
    "branchThumbnail": "images/branch_3.webp",
    "branchHref": "https://www.miracles-of-quran.com/physics.html",
    "domainHref": "https://www.miracles-of-quran.com/speed_of_light.html",
    "difficultyLevel": "चरम"
  },
  {
    "domainId": 57,
    "domainTitle": "अंतिम गति",
    "domainSubtitle": "फ्री-फॉल में उच्चतम गति।",
    "domainThumbnail": "images/domain_57.webp",
    "branchId": 3,
    "branchTitle": "भौतिक विज्ञान",
    "branchSubtitle": "अंतरिक्ष और समय के माध्यम से गति और व्यवहार का विज्ञान",
    "branchThumbnail": "images/branch_3.webp",
    "branchHref": "https://www.miracles-of-quran.com/physics.html",
    "domainHref": "https://www.miracles-of-quran.com/terminal_velocity.html",
    "difficultyLevel": "उन्नत"
  },
  {
    "domainId": 58,
    "domainTitle": "रेले स्कैटरिंग",
    "domainSubtitle": "आकाश को नीला दिखाई देने का कारण बनता है।",
    "domainThumbnail": "images/domain_58.webp",
    "branchId": 3,
    "branchTitle": "भौतिक विज्ञान",
    "branchSubtitle": "अंतरिक्ष और समय के माध्यम से गति और व्यवहार का विज्ञान",
    "branchThumbnail": "images/branch_3.webp",
    "branchHref": "https://www.miracles-of-quran.com/physics.html",
    "domainHref": "https://www.miracles-of-quran.com/rayleigh_scattering.html",
    "difficultyLevel": "चरम"
  },
  {
    "domainId": 59,
    "domainTitle": "जोड़े",
    "domainSubtitle": "जोड़े में सभी मामले।",
    "domainThumbnail": "images/domain_59.webp",
    "branchId": 3,
    "branchTitle": "भौतिक विज्ञान",
    "branchSubtitle": "अंतरिक्ष और समय के माध्यम से गति और व्यवहार का विज्ञान",
    "branchThumbnail": "images/branch_3.webp",
    "branchHref": "https://www.miracles-of-quran.com/physics.html",
    "domainHref": "https://www.miracles-of-quran.com/pairs.html",
    "difficultyLevel": "उन्नत"
  },
  {
    "domainId": 60,
    "domainTitle": "परमाणुओं",
    "domainSubtitle": "सबसे छोटा कण एक तार है।",
    "domainThumbnail": "images/domain_60.webp",
    "branchId": 3,
    "branchTitle": "भौतिक विज्ञान",
    "branchSubtitle": "अंतरिक्ष और समय के माध्यम से गति और व्यवहार का विज्ञान",
    "branchThumbnail": "images/branch_3.webp",
    "branchHref": "https://www.miracles-of-quran.com/physics.html",
    "domainHref": "https://www.miracles-of-quran.com/atoms.html",
    "difficultyLevel": "चरम"
  },
  {
    "domainId": 61,
    "domainTitle": "व्यक्तित्व",
    "domainSubtitle": "अरबी में भगवान का नाम ले जाता है।",
    "domainThumbnail": "images/domain_61.webp",
    "branchId": 3,
    "branchTitle": "भौतिक विज्ञान",
    "branchSubtitle": "अंतरिक्ष और समय के माध्यम से गति और व्यवहार का विज्ञान",
    "branchThumbnail": "images/branch_3.webp",
    "branchHref": "https://www.miracles-of-quran.com/physics.html",
    "domainHref": "https://www.miracles-of-quran.com/singularity.html",
    "difficultyLevel": "चरम"
  },
  {
    "domainId": 62,
    "domainTitle": "रोशनी",
    "domainSubtitle": "अदृश्य स्पेक्ट्रम।",
    "domainThumbnail": "images/domain_62.webp",
    "branchId": 3,
    "branchTitle": "भौतिक विज्ञान",
    "branchSubtitle": "अंतरिक्ष और समय के माध्यम से गति और व्यवहार का विज्ञान",
    "branchThumbnail": "images/branch_3.webp",
    "branchHref": "https://www.miracles-of-quran.com/physics.html",
    "domainHref": "https://www.miracles-of-quran.com/light.html",
    "difficultyLevel": "मध्यम"
  },
  {
    "domainId": 63,
    "domainTitle": "समय फैलाव",
    "domainSubtitle": "गुरुत्वाकर्षण में समय धीमा हो जाता है।",
    "domainThumbnail": "images/domain_63.webp",
    "branchId": 3,
    "branchTitle": "भौतिक विज्ञान",
    "branchSubtitle": "अंतरिक्ष और समय के माध्यम से गति और व्यवहार का विज्ञान",
    "branchThumbnail": "images/branch_3.webp",
    "branchHref": "https://www.miracles-of-quran.com/physics.html",
    "domainHref": "https://www.miracles-of-quran.com/time_dilation.html",
    "difficultyLevel": "चरम"
  },
  {
    "domainId": 64,
    "domainTitle": "wormholes",
    "domainSubtitle": "यातायात के लिए।",
    "domainThumbnail": "images/domain_64.webp",
    "branchId": 3,
    "branchTitle": "भौतिक विज्ञान",
    "branchSubtitle": "अंतरिक्ष और समय के माध्यम से गति और व्यवहार का विज्ञान",
    "branchThumbnail": "images/branch_3.webp",
    "branchHref": "https://www.miracles-of-quran.com/physics.html",
    "domainHref": "https://www.miracles-of-quran.com/wormholes.html",
    "difficultyLevel": "चरम"
  },
  {
    "domainId": 65,
    "domainTitle": "पल्सर",
    "domainSubtitle": "ब्लैक होल्स।",
    "domainThumbnail": "images/domain_65.webp",
    "branchId": 3,
    "branchTitle": "भौतिक विज्ञान",
    "branchSubtitle": "अंतरिक्ष और समय के माध्यम से गति और व्यवहार का विज्ञान",
    "branchThumbnail": "images/branch_3.webp",
    "branchHref": "https://www.miracles-of-quran.com/physics.html",
    "domainHref": "https://www.miracles-of-quran.com/pulsars_black_holes.html",
    "difficultyLevel": "चरम"
  },
  {
    "domainId": 66,
    "domainTitle": "गुरुत्वाकर्षण",
    "domainSubtitle": "स्पेसटाइम की वक्रता।",
    "domainThumbnail": "images/domain_66.webp",
    "branchId": 3,
    "branchTitle": "भौतिक विज्ञान",
    "branchSubtitle": "अंतरिक्ष और समय के माध्यम से गति और व्यवहार का विज्ञान",
    "branchThumbnail": "images/branch_3.webp",
    "branchHref": "https://www.miracles-of-quran.com/physics.html",
    "domainHref": "https://www.miracles-of-quran.com/gravity.html",
    "difficultyLevel": "चरम"
  },
  {
    "domainId": 67,
    "domainTitle": "अंतरिक्ष समय",
    "domainSubtitle": "मास कर्व्स स्पेसटाइम।",
    "domainThumbnail": "images/domain_67.webp",
    "branchId": 3,
    "branchTitle": "भौतिक विज्ञान",
    "branchSubtitle": "अंतरिक्ष और समय के माध्यम से गति और व्यवहार का विज्ञान",
    "branchThumbnail": "images/branch_3.webp",
    "branchHref": "https://www.miracles-of-quran.com/physics.html",
    "domainHref": "https://www.miracles-of-quran.com/spacetime.html",
    "difficultyLevel": "चरम"
  },
  {
    "domainId": 68,
    "domainTitle": "कवच भेदना",
    "domainSubtitle": "तांबे का प्रयोग।",
    "domainThumbnail": "images/domain_68.webp",
    "branchId": 3,
    "branchTitle": "भौतिक विज्ञान",
    "branchSubtitle": "अंतरिक्ष और समय के माध्यम से गति और व्यवहार का विज्ञान",
    "branchThumbnail": "images/branch_3.webp",
    "branchHref": "https://www.miracles-of-quran.com/physics.html",
    "domainHref": "https://www.miracles-of-quran.com/armor_piercing.html",
    "difficultyLevel": "मध्यम"
  },
  {
    "domainId": 69,
    "domainTitle": "गुरुत्वाकर्षण लहरों",
    "domainSubtitle": "स्पेसटाइम में तरंगें।",
    "domainThumbnail": "images/domain_69.webp",
    "branchId": 3,
    "branchTitle": "भौतिक विज्ञान",
    "branchSubtitle": "अंतरिक्ष और समय के माध्यम से गति और व्यवहार का विज्ञान",
    "branchThumbnail": "images/branch_3.webp",
    "branchHref": "https://www.miracles-of-quran.com/physics.html",
    "domainHref": "https://www.miracles-of-quran.com/gravitational_waves.html",
    "difficultyLevel": "चरम"
  },
  {
    "domainId": 70,
    "domainTitle": "सोनिक हथियार",
    "domainSubtitle": "अक्षम करना या मारना।",
    "domainThumbnail": "images/domain_70.webp",
    "branchId": 3,
    "branchTitle": "भौतिक विज्ञान",
    "branchSubtitle": "अंतरिक्ष और समय के माध्यम से गति और व्यवहार का विज्ञान",
    "branchThumbnail": "images/branch_3.webp",
    "branchHref": "https://www.miracles-of-quran.com/physics.html",
    "domainHref": "https://www.miracles-of-quran.com/sonic_weapons.html",
    "difficultyLevel": "उन्नत"
  },
  {
    "domainId": 71,
    "domainTitle": "द्रव्यमान",
    "domainSubtitle": "तारों का कंपन।",
    "domainThumbnail": "images/domain_71.webp",
    "branchId": 3,
    "branchTitle": "भौतिक विज्ञान",
    "branchSubtitle": "अंतरिक्ष और समय के माध्यम से गति और व्यवहार का विज्ञान",
    "branchThumbnail": "images/branch_3.webp",
    "branchHref": "https://www.miracles-of-quran.com/physics.html",
    "domainHref": "https://www.miracles-of-quran.com/mass.html",
    "difficultyLevel": "चरम"
  },
  {
    "domainId": 72,
    "domainTitle": "स्ट्रिंग सिद्धांत",
    "domainSubtitle": "अतिरिक्त आयामों में द्रव्यमान।",
    "domainThumbnail": "images/domain_72.webp",
    "branchId": 3,
    "branchTitle": "भौतिक विज्ञान",
    "branchSubtitle": "अंतरिक्ष और समय के माध्यम से गति और व्यवहार का विज्ञान",
    "branchThumbnail": "images/branch_3.webp",
    "branchHref": "https://www.miracles-of-quran.com/physics.html",
    "domainHref": "https://www.miracles-of-quran.com/string_theory.html",
    "difficultyLevel": "चरम"
  },
  {
    "domainId": 73,
    "domainTitle": "समानता सिद्धांत",
    "domainSubtitle": "त्वरण गुरुत्वाकर्षण के बराबर है।",
    "domainThumbnail": "images/domain_73.webp",
    "branchId": 3,
    "branchTitle": "भौतिक विज्ञान",
    "branchSubtitle": "अंतरिक्ष और समय के माध्यम से गति और व्यवहार का विज्ञान",
    "branchThumbnail": "images/branch_3.webp",
    "branchHref": "https://www.miracles-of-quran.com/physics.html",
    "domainHref": "https://www.miracles-of-quran.com/equivalence_principle.html",
    "difficultyLevel": "चरम"
  },
  {
    "domainId": 74,
    "domainTitle": "रेडशिफ्टिंग",
    "domainSubtitle": "दूरी के अनुपात में।",
    "domainThumbnail": "images/domain_74.webp",
    "branchId": 3,
    "branchTitle": "भौतिक विज्ञान",
    "branchSubtitle": "अंतरिक्ष और समय के माध्यम से गति और व्यवहार का विज्ञान",
    "branchThumbnail": "images/branch_3.webp",
    "branchHref": "https://www.miracles-of-quran.com/physics.html",
    "domainHref": "https://www.miracles-of-quran.com/redshifting.html",
    "difficultyLevel": "चरम"
  },
  {
    "domainId": 75,
    "domainTitle": "शीत प्लाज्मा",
    "domainSubtitle": "आग जो जलती नहीं।",
    "domainThumbnail": "images/domain_75.webp",
    "branchId": 3,
    "branchTitle": "भौतिक विज्ञान",
    "branchSubtitle": "अंतरिक्ष और समय के माध्यम से गति और व्यवहार का विज्ञान",
    "branchThumbnail": "images/branch_3.webp",
    "branchHref": "https://www.miracles-of-quran.com/physics.html",
    "domainHref": "https://www.miracles-of-quran.com/cold_plasma.html",
    "difficultyLevel": "चरम"
  },
  {
    "domainId": 76,
    "domainTitle": "कागज पैसे",
    "domainSubtitle": "धातु के सिक्कों के बजाय।",
    "domainThumbnail": "images/domain_76.webp",
    "branchId": 4,
    "branchTitle": "इतिहास",
    "branchSubtitle": "अतीत का अध्ययन",
    "branchThumbnail": "images/branch_4.webp",
    "branchHref": "https://www.miracles-of-quran.com/history.html",
    "domainHref": "https://www.miracles-of-quran.com/paper_money.html",
    "difficultyLevel": "आसान"
  },
  {
    "domainId": 77,
    "domainTitle": "चित्रलिपि",
    "domainSubtitle": "फिरौन का शोक।",
    "domainThumbnail": "images/domain_77.webp",
    "branchId": 13,
    "branchTitle": "मिसरशास्र",
    "branchSubtitle": "प्राचीन मिस्र का अध्ययन",
    "branchThumbnail": "images/branch_13.webp",
    "branchHref": "https://www.miracles-of-quran.com/egyptology.html",
    "domainHref": "https://www.miracles-of-quran.com/hieroglyphs.html",
    "difficultyLevel": "आसान"
  },
  {
    "domainId": 78,
    "domainTitle": "डिजिटल पुस्तकें",
    "domainSubtitle": "कागज की किताबें बदलें।",
    "domainThumbnail": "images/domain_78.webp",
    "branchId": 4,
    "branchTitle": "इतिहास",
    "branchSubtitle": "अतीत का अध्ययन",
    "branchThumbnail": "images/branch_4.webp",
    "branchHref": "https://www.miracles-of-quran.com/history.html",
    "domainHref": "https://www.miracles-of-quran.com/digital_books.html",
    "difficultyLevel": "मध्यम"
  },
  {
    "domainId": 79,
    "domainTitle": "पंचांग",
    "domainSubtitle": "सौर बनाम चंद्र।",
    "domainThumbnail": "images/domain_79.webp",
    "branchId": 4,
    "branchTitle": "इतिहास",
    "branchSubtitle": "अतीत का अध्ययन",
    "branchThumbnail": "images/branch_4.webp",
    "branchHref": "https://www.miracles-of-quran.com/history.html",
    "domainHref": "https://www.miracles-of-quran.com/calendar.html",
    "difficultyLevel": "आसान"
  },
  {
    "domainId": 80,
    "domainTitle": "मूसा",
    "domainSubtitle": "नाम का अर्थ \u0026quot;नवजात शिशु\u0026quot; है।",
    "domainThumbnail": "images/domain_80.webp",
    "branchId": 13,
    "branchTitle": "मिसरशास्र",
    "branchSubtitle": "प्राचीन मिस्र का अध्ययन",
    "branchThumbnail": "images/branch_13.webp",
    "branchHref": "https://www.miracles-of-quran.com/egyptology.html",
    "domainHref": "https://www.miracles-of-quran.com/moses.html",
    "difficultyLevel": "मध्यम"
  },
  {
    "domainId": 81,
    "domainTitle": "फिरौन की ममी",
    "domainSubtitle": "डूबा फिरौन मिला।",
    "domainThumbnail": "images/domain_81.webp",
    "branchId": 13,
    "branchTitle": "मिसरशास्र",
    "branchSubtitle": "प्राचीन मिस्र का अध्ययन",
    "branchThumbnail": "images/branch_13.webp",
    "branchHref": "https://www.miracles-of-quran.com/egyptology.html",
    "domainHref": "https://www.miracles-of-quran.com/mummy.html",
    "difficultyLevel": "मध्यम"
  },
  {
    "domainId": 82,
    "domainTitle": "हामान",
    "domainSubtitle": "मिस्र में।",
    "domainThumbnail": "images/domain_82.webp",
    "branchId": 13,
    "branchTitle": "मिसरशास्र",
    "branchSubtitle": "प्राचीन मिस्र का अध्ययन",
    "branchThumbnail": "images/branch_13.webp",
    "branchHref": "https://www.miracles-of-quran.com/egyptology.html",
    "domainHref": "https://www.miracles-of-quran.com/haman.html",
    "difficultyLevel": "मध्यम"
  },
  {
    "domainId": 83,
    "domainTitle": "कर्णक मंदिर",
    "domainSubtitle": "फिरौन द्वारा निर्मित स्तंभ।",
    "domainThumbnail": "images/domain_83.webp",
    "branchId": 13,
    "branchTitle": "मिसरशास्र",
    "branchSubtitle": "प्राचीन मिस्र का अध्ययन",
    "branchThumbnail": "images/branch_13.webp",
    "branchHref": "https://www.miracles-of-quran.com/egyptology.html",
    "domainHref": "https://www.miracles-of-quran.com/karnak.html",
    "difficultyLevel": "आसान"
  },
  {
    "domainId": 84,
    "domainTitle": "फिरौन",
    "domainSubtitle": "नया साम्राज्य।",
    "domainThumbnail": "images/domain_84.webp",
    "branchId": 13,
    "branchTitle": "मिसरशास्र",
    "branchSubtitle": "प्राचीन मिस्र का अध्ययन",
    "branchThumbnail": "images/branch_13.webp",
    "branchHref": "https://www.miracles-of-quran.com/egyptology.html",
    "domainHref": "https://www.miracles-of-quran.com/pharaoh.html",
    "difficultyLevel": "आसान"
  },
  {
    "domainId": 85,
    "domainTitle": "उड़ान",
    "domainSubtitle": "मनुष्य आकाश में पहुँच गया।",
    "domainThumbnail": "images/domain_85.webp",
    "branchId": 4,
    "branchTitle": "इतिहास",
    "branchSubtitle": "अतीत का अध्ययन",
    "branchThumbnail": "images/branch_4.webp",
    "branchHref": "https://www.miracles-of-quran.com/history.html",
    "domainHref": "https://www.miracles-of-quran.com/flight.html",
    "difficultyLevel": "आसान"
  },
  {
    "domainId": 86,
    "domainTitle": "नूह",
    "domainSubtitle": "स्थानीय बाढ़, वैश्विक नहीं।",
    "domainThumbnail": "images/domain_86.webp",
    "branchId": 4,
    "branchTitle": "इतिहास",
    "branchSubtitle": "अतीत का अध्ययन",
    "branchThumbnail": "images/branch_4.webp",
    "branchHref": "https://www.miracles-of-quran.com/history.html",
    "domainHref": "https://www.miracles-of-quran.com/noah.html",
    "difficultyLevel": "मध्यम"
  },
  {
    "domainId": 87,
    "domainTitle": "देवताओं",
    "domainSubtitle": "फिरौन देवताओं के रूप में पूजे जाते थे।",
    "domainThumbnail": "images/domain_87.webp",
    "branchId": 13,
    "branchTitle": "मिसरशास्र",
    "branchSubtitle": "प्राचीन मिस्र का अध्ययन",
    "branchThumbnail": "images/branch_13.webp",
    "branchHref": "https://www.miracles-of-quran.com/egyptology.html",
    "domainHref": "https://www.miracles-of-quran.com/deities.html",
    "difficultyLevel": "आसान"
  },
  {
    "domainId": 88,
    "domainTitle": "पॉम्पी",
    "domainSubtitle": "अपने अंतिम कार्य में जमे हुए।",
    "domainThumbnail": "images/domain_88.webp",
    "branchId": 4,
    "branchTitle": "इतिहास",
    "branchSubtitle": "अतीत का अध्ययन",
    "branchThumbnail": "images/branch_4.webp",
    "branchHref": "https://www.miracles-of-quran.com/history.html",
    "domainHref": "https://www.miracles-of-quran.com/pompeii.html",
    "difficultyLevel": "मध्यम"
  },
  {
    "domainId": 89,
    "domainTitle": "उत्तर",
    "domainSubtitle": "दिशाओं के लिए मानक।",
    "domainThumbnail": "images/domain_89.webp",
    "branchId": 4,
    "branchTitle": "इतिहास",
    "branchSubtitle": "अतीत का अध्ययन",
    "branchThumbnail": "images/branch_4.webp",
    "branchHref": "https://www.miracles-of-quran.com/history.html",
    "domainHref": "https://www.miracles-of-quran.com/north.html",
    "difficultyLevel": "मध्यम"
  },
  {
    "domainId": 90,
    "domainTitle": "पेट्रा",
    "domainSubtitle": "खोया शहर।",
    "domainThumbnail": "images/domain_90.webp",
    "branchId": 4,
    "branchTitle": "इतिहास",
    "branchSubtitle": "अतीत का अध्ययन",
    "branchThumbnail": "images/branch_4.webp",
    "branchHref": "https://www.miracles-of-quran.com/history.html",
    "domainHref": "https://www.miracles-of-quran.com/petra.html",
    "difficultyLevel": "आसान"
  },
  {
    "domainId": 91,
    "domainTitle": "उबार",
    "domainSubtitle": "बाढ़ में डूबा शहर।",
    "domainThumbnail": "images/domain_91.webp",
    "branchId": 4,
    "branchTitle": "इतिहास",
    "branchSubtitle": "अतीत का अध्ययन",
    "branchThumbnail": "images/branch_4.webp",
    "branchHref": "https://www.miracles-of-quran.com/history.html",
    "domainHref": "https://www.miracles-of-quran.com/ubar.html",
    "difficultyLevel": "आसान"
  },
  {
    "domainId": 92,
    "domainTitle": "सूली पर चढ़ाया",
    "domainSubtitle": "फिरौन द्वारा।",
    "domainThumbnail": "images/domain_92.webp",
    "branchId": 13,
    "branchTitle": "मिसरशास्र",
    "branchSubtitle": "प्राचीन मिस्र का अध्ययन",
    "branchThumbnail": "images/branch_13.webp",
    "branchHref": "https://www.miracles-of-quran.com/egyptology.html",
    "domainHref": "https://www.miracles-of-quran.com/crucifixion.html",
    "difficultyLevel": "मध्यम"
  },
  {
    "domainId": 93,
    "domainTitle": "दरवाज़े के ताले",
    "domainSubtitle": "मिस्रियों द्वारा आविष्कार किया गया।",
    "domainThumbnail": "images/domain_93.webp",
    "branchId": 13,
    "branchTitle": "मिसरशास्र",
    "branchSubtitle": "प्राचीन मिस्र का अध्ययन",
    "branchThumbnail": "images/branch_13.webp",
    "branchHref": "https://www.miracles-of-quran.com/egyptology.html",
    "domainHref": "https://www.miracles-of-quran.com/door_locks.html",
    "difficultyLevel": "आसान"
  },
  {
    "domainId": 95,
    "domainTitle": "पूर्णचंद्र",
    "domainSubtitle": "रात में ही देखा जा सकता है।",
    "domainThumbnail": "images/domain_95.webp",
    "branchId": 5,
    "branchTitle": "खगोल",
    "branchSubtitle": "आकाशीय पिंडों का विज्ञान",
    "branchThumbnail": "images/branch_5.jpg",
    "branchHref": "https://www.miracles-of-quran.com/astronomy.html",
    "domainHref": "https://www.miracles-of-quran.com/full_moon.html",
    "difficultyLevel": "उन्नत"
  },
  {
    "domainId": 96,
    "domainTitle": "लोहा",
    "domainSubtitle": "सबसे मजबूत बाध्य नाभिक।",
    "domainThumbnail": "images/domain_96.webp",
    "branchId": 8,
    "branchTitle": "रसायन शास्त्र",
    "branchSubtitle": "तत्वों और यौगिकों का विज्ञान",
    "branchThumbnail": "images/branch_8.webp",
    "branchHref": "https://www.miracles-of-quran.com/chemistry.html",
    "domainHref": "https://www.miracles-of-quran.com/iron.html",
    "difficultyLevel": "मध्यम"
  },
  {
    "domainId": 97,
    "domainTitle": "उल्कापिंड",
    "domainSubtitle": "वातावरण में जलना।",
    "domainThumbnail": "images/domain_97.webp",
    "branchId": 5,
    "branchTitle": "खगोल",
    "branchSubtitle": "आकाशीय पिंडों का विज्ञान",
    "branchThumbnail": "images/branch_5.jpg",
    "branchHref": "https://www.miracles-of-quran.com/astronomy.html",
    "domainHref": "https://www.miracles-of-quran.com/meteorites.html",
    "difficultyLevel": "उन्नत"
  },
  {
    "domainId": 98,
    "domainTitle": "exoplanets",
    "domainSubtitle": "हमारे सौर मंडल के बाहर के ग्रह।",
    "domainThumbnail": "images/domain_98.webp",
    "branchId": 5,
    "branchTitle": "खगोल",
    "branchSubtitle": "आकाशीय पिंडों का विज्ञान",
    "branchThumbnail": "images/branch_5.jpg",
    "branchHref": "https://www.miracles-of-quran.com/astronomy.html",
    "domainHref": "https://www.miracles-of-quran.com/exoplanets.html",
    "difficultyLevel": "चरम"
  },
  {
    "domainId": 99,
    "domainTitle": "ग्रहों की कक्षाएँ",
    "domainSubtitle": "सभी तारों और ग्रहों की कक्षाएँ होती हैं।",
    "domainThumbnail": "images/domain_99.webp",
    "branchId": 5,
    "branchTitle": "खगोल",
    "branchSubtitle": "आकाशीय पिंडों का विज्ञान",
    "branchThumbnail": "images/branch_5.jpg",
    "branchHref": "https://www.miracles-of-quran.com/astronomy.html",
    "domainHref": "https://www.miracles-of-quran.com/planetary_orbits.html",
    "difficultyLevel": "उन्नत"
  },
  {
    "domainId": 100,
    "domainTitle": "पानी",
    "domainSubtitle": "बाह्य अंतरिक्ष में धूमकेतुओं से आया है।",
    "domainThumbnail": "images/domain_100.webp",
    "branchId": 5,
    "branchTitle": "खगोल",
    "branchSubtitle": "आकाशीय पिंडों का विज्ञान",
    "branchThumbnail": "images/branch_5.jpg",
    "branchHref": "https://www.miracles-of-quran.com/astronomy.html",
    "domainHref": "https://www.miracles-of-quran.com/water.html",
    "difficultyLevel": "मध्यम"
  },
  {
    "domainId": 101,
    "domainTitle": "सूरज की रोशनी",
    "domainSubtitle": "देरी से पहली धूप।",
    "domainThumbnail": "images/domain_101.webp",
    "branchId": 5,
    "branchTitle": "खगोल",
    "branchSubtitle": "आकाशीय पिंडों का विज्ञान",
    "branchThumbnail": "images/branch_5.jpg",
    "branchHref": "https://www.miracles-of-quran.com/astronomy.html",
    "domainHref": "https://www.miracles-of-quran.com/sunlight.html",
    "difficultyLevel": "उन्नत"
  },
  {
    "domainId": 102,
    "domainTitle": "मैग्नेटोस्फीयर",
    "domainSubtitle": "लौकिक विकिरण से ढाल।",
    "domainThumbnail": "images/domain_102.webp",
    "branchId": 5,
    "branchTitle": "खगोल",
    "branchSubtitle": "आकाशीय पिंडों का विज्ञान",
    "branchThumbnail": "images/branch_5.jpg",
    "branchHref": "https://www.miracles-of-quran.com/astronomy.html",
    "domainHref": "https://www.miracles-of-quran.com/magnetosphere.html",
    "difficultyLevel": "उन्नत"
  },
  {
    "domainId": 103,
    "domainTitle": "चांदनी",
    "domainSubtitle": "चन्द्रमा सूर्य के प्रकाश को परावर्तित करता है।",
    "domainThumbnail": "images/domain_103.webp",
    "branchId": 5,
    "branchTitle": "खगोल",
    "branchSubtitle": "आकाशीय पिंडों का विज्ञान",
    "branchThumbnail": "images/branch_5.jpg",
    "branchHref": "https://www.miracles-of-quran.com/astronomy.html",
    "domainHref": "https://www.miracles-of-quran.com/moonlight.html",
    "difficultyLevel": "आसान"
  },
  {
    "domainId": 104,
    "domainTitle": "दिन",
    "domainSubtitle": "दिन लंबा होता जा रहा है।",
    "domainThumbnail": "images/domain_104.webp",
    "branchId": 5,
    "branchTitle": "खगोल",
    "branchSubtitle": "आकाशीय पिंडों का विज्ञान",
    "branchThumbnail": "images/branch_5.jpg",
    "branchHref": "https://www.miracles-of-quran.com/astronomy.html",
    "domainHref": "https://www.miracles-of-quran.com/day.html",
    "difficultyLevel": "उन्नत"
  },
  {
    "domainId": 105,
    "domainTitle": "मल्टी स्टार सिस्टम",
    "domainSubtitle": "ग्रह कई सितारों की परिक्रमा कर रहा है।",
    "domainThumbnail": "images/domain_105.jpg",
    "branchId": 5,
    "branchTitle": "खगोल",
    "branchSubtitle": "आकाशीय पिंडों का विज्ञान",
    "branchThumbnail": "images/branch_5.jpg",
    "branchHref": "https://www.miracles-of-quran.com/astronomy.html",
    "domainHref": "https://www.miracles-of-quran.com/multi_star_system.html",
    "difficultyLevel": "चरम"
  },
  {
    "domainId": 106,
    "domainTitle": "सौर भड़काव",
    "domainSubtitle": "कोरोनल मास इजेक्शन।",
    "domainThumbnail": "images/domain_106.webp",
    "branchId": 5,
    "branchTitle": "खगोल",
    "branchSubtitle": "आकाशीय पिंडों का विज्ञान",
    "branchThumbnail": "images/branch_5.jpg",
    "branchHref": "https://www.miracles-of-quran.com/astronomy.html",
    "domainHref": "https://www.miracles-of-quran.com/solar_flare.html",
    "difficultyLevel": "चरम"
  },
  {
    "domainId": 107,
    "domainTitle": "तारों का",
    "domainSubtitle": "चमक मंच के साथ बदलती है।",
    "domainThumbnail": "images/domain_107.webp",
    "branchId": 5,
    "branchTitle": "खगोल",
    "branchSubtitle": "आकाशीय पिंडों का विज्ञान",
    "branchThumbnail": "images/branch_5.jpg",
    "branchHref": "https://www.miracles-of-quran.com/astronomy.html",
    "domainHref": "https://www.miracles-of-quran.com/starlight.html",
    "difficultyLevel": "चरम"
  },
  {
    "domainId": 108,
    "domainTitle": "सीरियस",
    "domainSubtitle": "प्रकाश वर्ष और त्रिज्या में दूरी।",
    "domainThumbnail": "images/domain_108.webp",
    "branchId": 5,
    "branchTitle": "खगोल",
    "branchSubtitle": "आकाशीय पिंडों का विज्ञान",
    "branchThumbnail": "images/branch_5.jpg",
    "branchHref": "https://www.miracles-of-quran.com/astronomy.html",
    "domainHref": "https://www.miracles-of-quran.com/sirius.html",
    "difficultyLevel": "मध्यम"
  },
  {
    "domainId": 109,
    "domainTitle": "सितारे डगमगाते हैं",
    "domainSubtitle": "बेरिकेंटर के आसपास।",
    "domainThumbnail": "images/domain_109.webp",
    "branchId": 5,
    "branchTitle": "खगोल",
    "branchSubtitle": "आकाशीय पिंडों का विज्ञान",
    "branchThumbnail": "images/branch_5.jpg",
    "branchHref": "https://www.miracles-of-quran.com/astronomy.html",
    "domainHref": "https://www.miracles-of-quran.com/stars_wobble.html",
    "difficultyLevel": "उन्नत"
  },
  {
    "domainId": 110,
    "domainTitle": "शुक्र",
    "domainSubtitle": "हमारे सौर मंडल के अंदर एक ग्रह।",
    "domainThumbnail": "images/domain_110.webp",
    "branchId": 4,
    "branchTitle": "इतिहास",
    "branchSubtitle": "अतीत का अध्ययन",
    "branchThumbnail": "images/branch_4.webp",
    "branchHref": "https://www.miracles-of-quran.com/history.html",
    "domainHref": "https://www.miracles-of-quran.com/venus.html",
    "difficultyLevel": "आसान"
  },
  {
    "domainId": 111,
    "domainTitle": "ग्रहों",
    "domainSubtitle": "बिखेर सकता है।",
    "domainThumbnail": "images/domain_111.webp",
    "branchId": 5,
    "branchTitle": "खगोल",
    "branchSubtitle": "आकाशीय पिंडों का विज्ञान",
    "branchThumbnail": "images/branch_5.jpg",
    "branchHref": "https://www.miracles-of-quran.com/astronomy.html",
    "domainHref": "https://www.miracles-of-quran.com/planets.html",
    "difficultyLevel": "उन्नत"
  },
  {
    "domainId": 112,
    "domainTitle": "केल्विन",
    "domainSubtitle": "सूर्य की सतह का तापमान।",
    "domainThumbnail": "images/domain_112.webp",
    "branchId": 5,
    "branchTitle": "खगोल",
    "branchSubtitle": "आकाशीय पिंडों का विज्ञान",
    "branchThumbnail": "images/branch_5.jpg",
    "branchHref": "https://www.miracles-of-quran.com/astronomy.html",
    "domainHref": "https://www.miracles-of-quran.com/kelvin.html",
    "difficultyLevel": "आसान"
  },
  {
    "domainId": 113,
    "domainTitle": "चींटियों",
    "domainSubtitle": "पंखहीन चींटियाँ सभी मादा होती हैं।",
    "domainThumbnail": "images/domain_113.webp",
    "branchId": 6,
    "branchTitle": "प्राणि विज्ञान",
    "branchSubtitle": "पशु विज्ञान",
    "branchThumbnail": "images/branch_6.webp",
    "branchHref": "https://www.miracles-of-quran.com/zoology.html",
    "domainHref": "https://www.miracles-of-quran.com/ants.html",
    "difficultyLevel": "आसान"
  },
  {
    "domainId": 114,
    "domainTitle": "रैप्टर्स",
    "domainSubtitle": "मांस खाने वाले पक्षी।",
    "domainThumbnail": "images/domain_114.webp",
    "branchId": 6,
    "branchTitle": "प्राणि विज्ञान",
    "branchSubtitle": "पशु विज्ञान",
    "branchThumbnail": "images/branch_6.webp",
    "branchHref": "https://www.miracles-of-quran.com/zoology.html",
    "domainHref": "https://www.miracles-of-quran.com/raptors.html",
    "difficultyLevel": "मध्यम"
  },
  {
    "domainId": 115,
    "domainTitle": "मकड़ी का जाला",
    "domainSubtitle": "महिलाओं द्वारा निर्मित।",
    "domainThumbnail": "images/domain_115.webp",
    "branchId": 6,
    "branchTitle": "प्राणि विज्ञान",
    "branchSubtitle": "पशु विज्ञान",
    "branchThumbnail": "images/branch_6.webp",
    "branchHref": "https://www.miracles-of-quran.com/zoology.html",
    "domainHref": "https://www.miracles-of-quran.com/spider_web.html",
    "difficultyLevel": "मध्यम"
  },
  {
    "domainId": 116,
    "domainTitle": "शहद की मक्खियाँ",
    "domainSubtitle": "सभी श्रमिक मधुमक्खियाँ मादा होती हैं और ठोस चट्टान में ड्रिल करती हैं।",
    "domainThumbnail": "images/domain_116.webp",
    "branchId": 6,
    "branchTitle": "प्राणि विज्ञान",
    "branchSubtitle": "पशु विज्ञान",
    "branchThumbnail": "images/branch_6.webp",
    "branchHref": "https://www.miracles-of-quran.com/zoology.html",
    "domainHref": "https://www.miracles-of-quran.com/honey_bees.html",
    "difficultyLevel": "मध्यम"
  },
  {
    "domainId": 117,
    "domainTitle": "कालोनियों",
    "domainSubtitle": "सामाजिक उपनिवेश।",
    "domainThumbnail": "images/domain_117.webp",
    "branchId": 6,
    "branchTitle": "प्राणि विज्ञान",
    "branchSubtitle": "पशु विज्ञान",
    "branchThumbnail": "images/branch_6.webp",
    "branchHref": "https://www.miracles-of-quran.com/zoology.html",
    "domainHref": "https://www.miracles-of-quran.com/colonies.html",
    "difficultyLevel": "आसान"
  },
  {
    "domainId": 118,
    "domainTitle": "पशु भाषाएँ",
    "domainSubtitle": "जानवरों की अपनी भाषाएं होती हैं।",
    "domainThumbnail": "images/domain_118.jpeg",
    "branchId": 6,
    "branchTitle": "प्राणि विज्ञान",
    "branchSubtitle": "पशु विज्ञान",
    "branchThumbnail": "images/branch_6.webp",
    "branchHref": "https://www.miracles-of-quran.com/zoology.html",
    "domainHref": "https://www.miracles-of-quran.com/animal_languages.html",
    "difficultyLevel": "आसान"
  },
  {
    "domainId": 119,
    "domainTitle": "मच्छर",
    "domainSubtitle": "उनके अपने परजीवी हैं।",
    "domainThumbnail": "images/domain_119.webp",
    "branchId": 6,
    "branchTitle": "प्राणि विज्ञान",
    "branchSubtitle": "पशु विज्ञान",
    "branchThumbnail": "images/branch_6.webp",
    "branchHref": "https://www.miracles-of-quran.com/zoology.html",
    "domainHref": "https://www.miracles-of-quran.com/mosquito.html",
    "difficultyLevel": "मध्यम"
  },
  {
    "domainId": 120,
    "domainTitle": "कौआ",
    "domainSubtitle": "उनके मृतकों के लिए अंतिम संस्कार करें।",
    "domainThumbnail": "images/domain_120.jpeg",
    "branchId": 6,
    "branchTitle": "प्राणि विज्ञान",
    "branchSubtitle": "पशु विज्ञान",
    "branchThumbnail": "images/branch_6.webp",
    "branchHref": "https://www.miracles-of-quran.com/zoology.html",
    "domainHref": "https://www.miracles-of-quran.com/crow.html",
    "difficultyLevel": "आसान"
  },
  {
    "domainId": 121,
    "domainTitle": "निशाचर जानवर",
    "domainSubtitle": "रात में सक्रिय।",
    "domainThumbnail": "images/domain_121.webp",
    "branchId": 6,
    "branchTitle": "प्राणि विज्ञान",
    "branchSubtitle": "पशु विज्ञान",
    "branchThumbnail": "images/branch_6.webp",
    "branchHref": "https://www.miracles-of-quran.com/zoology.html",
    "domainHref": "https://www.miracles-of-quran.com/nocturnal_animals.html",
    "difficultyLevel": "आसान"
  },
  {
    "domainId": 122,
    "domainTitle": "घरेलू मक्खी",
    "domainSubtitle": "केवल तरल पदार्थ चूस सकता है।",
    "domainThumbnail": "images/domain_122.webp",
    "branchId": 6,
    "branchTitle": "प्राणि विज्ञान",
    "branchSubtitle": "पशु विज्ञान",
    "branchThumbnail": "images/branch_6.webp",
    "branchHref": "https://www.miracles-of-quran.com/zoology.html",
    "domainHref": "https://www.miracles-of-quran.com/housefly.html",
    "difficultyLevel": "मध्यम"
  },
  {
    "domainId": 123,
    "domainTitle": "जीवाश्मों",
    "domainSubtitle": "प्राकृतिक रूप से सुरक्षित रखता है।",
    "domainThumbnail": "images/domain_123.webp",
    "branchId": 6,
    "branchTitle": "प्राणि विज्ञान",
    "branchSubtitle": "पशु विज्ञान",
    "branchThumbnail": "images/branch_6.webp",
    "branchHref": "https://www.miracles-of-quran.com/zoology.html",
    "domainHref": "https://www.miracles-of-quran.com/fossils.html",
    "difficultyLevel": "आसान"
  },
  {
    "domainId": 124,
    "domainTitle": "ऊंट",
    "domainSubtitle": "सबसे तेज पीने वाले।",
    "domainThumbnail": "images/domain_124.webp",
    "branchId": 6,
    "branchTitle": "प्राणि विज्ञान",
    "branchSubtitle": "पशु विज्ञान",
    "branchThumbnail": "images/branch_6.webp",
    "branchHref": "https://www.miracles-of-quran.com/zoology.html",
    "domainHref": "https://www.miracles-of-quran.com/camels.html",
    "difficultyLevel": "आसान"
  },
  {
    "domainId": 125,
    "domainTitle": "समुद्र की हवा",
    "domainSubtitle": "हवा की दिशा में उलटा।",
    "domainThumbnail": "images/domain_125.webp",
    "branchId": 7,
    "branchTitle": "अंतरिक्ष-विज्ञान",
    "branchSubtitle": "वातावरण का अध्ययन",
    "branchThumbnail": "images/branch_7.webp",
    "branchHref": "https://www.miracles-of-quran.com/meteorology.html",
    "domainHref": "https://www.miracles-of-quran.com/sea_breeze.html",
    "difficultyLevel": "मध्यम"
  },
  {
    "domainId": 126,
    "domainTitle": "ओरोग्राफिक प्रभाव",
    "domainSubtitle": "पहाड़ बारिश को ट्रिगर कर सकते हैं।",
    "domainThumbnail": "images/domain_126.jpg",
    "branchId": 7,
    "branchTitle": "अंतरिक्ष-विज्ञान",
    "branchSubtitle": "वातावरण का अध्ययन",
    "branchThumbnail": "images/branch_7.webp",
    "branchHref": "https://www.miracles-of-quran.com/meteorology.html",
    "domainHref": "https://www.miracles-of-quran.com/orographic_effect.html",
    "difficultyLevel": "मध्यम"
  },
  {
    "domainId": 127,
    "domainTitle": "हवा",
    "domainSubtitle": "पेड़ काट सकते हैं।",
    "domainThumbnail": "images/domain_127.webp",
    "branchId": 7,
    "branchTitle": "अंतरिक्ष-विज्ञान",
    "branchSubtitle": "वातावरण का अध्ययन",
    "branchThumbnail": "images/branch_7.webp",
    "branchHref": "https://www.miracles-of-quran.com/meteorology.html",
    "domainHref": "https://www.miracles-of-quran.com/wind.html",
    "difficultyLevel": "आसान"
  },
  {
    "domainId": 128,
    "domainTitle": "ज्वालामुखीय गैसें",
    "domainSubtitle": "अम्लीय वर्षा के कारण।",
    "domainThumbnail": "images/domain_128.webp",
    "branchId": 7,
    "branchTitle": "अंतरिक्ष-विज्ञान",
    "branchSubtitle": "वातावरण का अध्ययन",
    "branchThumbnail": "images/branch_7.webp",
    "branchHref": "https://www.miracles-of-quran.com/meteorology.html",
    "domainHref": "https://www.miracles-of-quran.com/volcanic_gases.html",
    "difficultyLevel": "उन्नत"
  },
  {
    "domainId": 129,
    "domainTitle": "माइक्रोबर्स्ट",
    "domainSubtitle": "विमानन के लिए खतरा।",
    "domainThumbnail": "images/domain_129.webp",
    "branchId": 7,
    "branchTitle": "अंतरिक्ष-विज्ञान",
    "branchSubtitle": "वातावरण का अध्ययन",
    "branchThumbnail": "images/branch_7.webp",
    "branchHref": "https://www.miracles-of-quran.com/meteorology.html",
    "domainHref": "https://www.miracles-of-quran.com/microburst.html",
    "difficultyLevel": "चरम"
  },
  {
    "domainId": 130,
    "domainTitle": "बादलों का भार",
    "domainSubtitle": "औसत मिलियन पाउंड है।",
    "domainThumbnail": "images/domain_130.webp",
    "branchId": 7,
    "branchTitle": "अंतरिक्ष-विज्ञान",
    "branchSubtitle": "वातावरण का अध्ययन",
    "branchThumbnail": "images/branch_7.webp",
    "branchHref": "https://www.miracles-of-quran.com/meteorology.html",
    "domainHref": "https://www.miracles-of-quran.com/clouds_weight.html",
    "difficultyLevel": "आसान"
  },
  {
    "domainId": 131,
    "domainTitle": "वायुमंडल",
    "domainSubtitle": "उल्कापिंडों से ढाल।",
    "domainThumbnail": "images/domain_131.webp",
    "branchId": 7,
    "branchTitle": "अंतरिक्ष-विज्ञान",
    "branchSubtitle": "वातावरण का अध्ययन",
    "branchThumbnail": "images/branch_7.webp",
    "branchHref": "https://www.miracles-of-quran.com/meteorology.html",
    "domainHref": "https://www.miracles-of-quran.com/atmosphere.html",
    "difficultyLevel": "मध्यम"
  },
  {
    "domainId": 132,
    "domainTitle": "ओस",
    "domainSubtitle": "शुष्क क्षेत्रों तक पहुँचता है।",
    "domainThumbnail": "images/domain_132.webp",
    "branchId": 7,
    "branchTitle": "अंतरिक्ष-विज्ञान",
    "branchSubtitle": "वातावरण का अध्ययन",
    "branchThumbnail": "images/branch_7.webp",
    "branchHref": "https://www.miracles-of-quran.com/meteorology.html",
    "domainHref": "https://www.miracles-of-quran.com/dew.html",
    "difficultyLevel": "आसान"
  },
  {
    "domainId": 133,
    "domainTitle": "बादल छाना",
    "domainSubtitle": "ट्रिगर बारिश।",
    "domainThumbnail": "images/domain_133.webp",
    "branchId": 7,
    "branchTitle": "अंतरिक्ष-विज्ञान",
    "branchSubtitle": "वातावरण का अध्ययन",
    "branchThumbnail": "images/branch_7.webp",
    "branchHref": "https://www.miracles-of-quran.com/meteorology.html",
    "domainHref": "https://www.miracles-of-quran.com/cloud_seeding.html",
    "difficultyLevel": "उन्नत"
  },
  {
    "domainId": 134,
    "domainTitle": "तटरेखा",
    "domainSubtitle": "ग्लोबल वार्मिंग के कारण पीछे हटना।",
    "domainThumbnail": "images/domain_134.webp",
    "branchId": 7,
    "branchTitle": "अंतरिक्ष-विज्ञान",
    "branchSubtitle": "वातावरण का अध्ययन",
    "branchThumbnail": "images/branch_7.webp",
    "branchHref": "https://www.miracles-of-quran.com/meteorology.html",
    "domainHref": "https://www.miracles-of-quran.com/shorelines.html",
    "difficultyLevel": "मध्यम"
  },
  {
    "domainId": 135,
    "domainTitle": "अग्नि भंवर",
    "domainSubtitle": "आग से प्रेरित।",
    "domainThumbnail": "images/domain_135.webp",
    "branchId": 7,
    "branchTitle": "अंतरिक्ष-विज्ञान",
    "branchSubtitle": "वातावरण का अध्ययन",
    "branchThumbnail": "images/branch_7.webp",
    "branchHref": "https://www.miracles-of-quran.com/meteorology.html",
    "domainHref": "https://www.miracles-of-quran.com/fire_whirl.html",
    "difficultyLevel": "मध्यम"
  },
  {
    "domainId": 136,
    "domainTitle": "मीठे पानी में",
    "domainSubtitle": "पहाड़ों पर।",
    "domainThumbnail": "images/domain_136.webp",
    "branchId": 7,
    "branchTitle": "अंतरिक्ष-विज्ञान",
    "branchSubtitle": "वातावरण का अध्ययन",
    "branchThumbnail": "images/branch_7.webp",
    "branchHref": "https://www.miracles-of-quran.com/meteorology.html",
    "domainHref": "https://www.miracles-of-quran.com/freshwater.html",
    "difficultyLevel": "आसान"
  },
  {
    "domainId": 137,
    "domainTitle": "अचानक आई बाढ़",
    "domainSubtitle": "पानी में अचानक उछाल।",
    "domainThumbnail": "images/domain_137.webp",
    "branchId": 7,
    "branchTitle": "अंतरिक्ष-विज्ञान",
    "branchSubtitle": "वातावरण का अध्ययन",
    "branchThumbnail": "images/branch_7.webp",
    "branchHref": "https://www.miracles-of-quran.com/meteorology.html",
    "domainHref": "https://www.miracles-of-quran.com/flash_flood.html",
    "difficultyLevel": "उन्नत"
  },
  {
    "domainId": 138,
    "domainTitle": "वायुमण्डलीय दबाव",
    "domainSubtitle": "ऊँचाई के साथ घटता है।",
    "domainThumbnail": "images/domain_138.webp",
    "branchId": 7,
    "branchTitle": "अंतरिक्ष-विज्ञान",
    "branchSubtitle": "वातावरण का अध्ययन",
    "branchThumbnail": "images/branch_7.webp",
    "branchHref": "https://www.miracles-of-quran.com/meteorology.html",
    "domainHref": "https://www.miracles-of-quran.com/atmospheric_pressure.html",
    "difficultyLevel": "आसान"
  },
  {
    "domainId": 139,
    "domainTitle": "जल चक्र",
    "domainSubtitle": "सूर्य की भूमिका।",
    "domainThumbnail": "images/domain_139.webp",
    "branchId": 7,
    "branchTitle": "अंतरिक्ष-विज्ञान",
    "branchSubtitle": "वातावरण का अध्ययन",
    "branchThumbnail": "images/branch_7.webp",
    "branchHref": "https://www.miracles-of-quran.com/meteorology.html",
    "domainHref": "https://www.miracles-of-quran.com/water_cycle.html",
    "difficultyLevel": "आसान"
  },
  {
    "domainId": 140,
    "domainTitle": "हाइड्रोजन",
    "domainSubtitle": "सूर्य मुख्य रूप से हाइड्रोजन।",
    "domainThumbnail": "images/domain_140.webp",
    "branchId": 8,
    "branchTitle": "रसायन शास्त्र",
    "branchSubtitle": "तत्वों और यौगिकों का विज्ञान",
    "branchThumbnail": "images/branch_8.webp",
    "branchHref": "https://www.miracles-of-quran.com/chemistry.html",
    "domainHref": "https://www.miracles-of-quran.com/hydrogen.html",
    "difficultyLevel": "आसान"
  },
  {
    "domainId": 141,
    "domainTitle": "सुपरियोनिक जल",
    "domainSubtitle": "काला और चिपचिपा।",
    "domainThumbnail": "images/domain_141.webp",
    "branchId": 8,
    "branchTitle": "रसायन शास्त्र",
    "branchSubtitle": "तत्वों और यौगिकों का विज्ञान",
    "branchThumbnail": "images/branch_8.webp",
    "branchHref": "https://www.miracles-of-quran.com/chemistry.html",
    "domainHref": "https://www.miracles-of-quran.com/superionic_water.html",
    "difficultyLevel": "चरम"
  },
  {
    "domainId": 142,
    "domainTitle": "अम्ल वर्षा",
    "domainSubtitle": "बड़े पैमाने पर विलुप्त होने का कारण बना।",
    "domainThumbnail": "images/domain_142.webp",
    "branchId": 8,
    "branchTitle": "रसायन शास्त्र",
    "branchSubtitle": "तत्वों और यौगिकों का विज्ञान",
    "branchThumbnail": "images/branch_8.webp",
    "branchHref": "https://www.miracles-of-quran.com/chemistry.html",
    "domainHref": "https://www.miracles-of-quran.com/acid_rain.html",
    "difficultyLevel": "चरम"
  },
  {
    "domainId": 143,
    "domainTitle": "भाप विस्फोट",
    "domainSubtitle": "सुपरहीट पानी फट सकता है।",
    "domainThumbnail": "images/domain_143.webp",
    "branchId": 14,
    "branchTitle": "जल विज्ञान",
    "branchSubtitle": "पृथ्वी के तरल पदार्थों का अध्ययन",
    "branchThumbnail": "images/branch_14.webp",
    "branchHref": "https://www.miracles-of-quran.com/hydrology.html",
    "domainHref": "https://www.miracles-of-quran.com/steam_explosions.html",
    "difficultyLevel": "उन्नत"
  },
  {
    "domainId": 144,
    "domainTitle": "पिरामिड",
    "domainSubtitle": "ऊपरी भाग पकी हुई मिट्टी है।",
    "domainThumbnail": "images/domain_144.webp",
    "branchId": 8,
    "branchTitle": "रसायन शास्त्र",
    "branchSubtitle": "तत्वों और यौगिकों का विज्ञान",
    "branchThumbnail": "images/branch_8.webp",
    "branchHref": "https://www.miracles-of-quran.com/chemistry.html",
    "domainHref": "https://www.miracles-of-quran.com/pyramids.html",
    "difficultyLevel": "मध्यम"
  },
  {
    "domainId": 145,
    "domainTitle": "श्यानता",
    "domainSubtitle": "प्रवाह का प्रतिरोध।",
    "domainThumbnail": "images/domain_145.webp",
    "branchId": 8,
    "branchTitle": "रसायन शास्त्र",
    "branchSubtitle": "तत्वों और यौगिकों का विज्ञान",
    "branchThumbnail": "images/branch_8.webp",
    "branchHref": "https://www.miracles-of-quran.com/chemistry.html",
    "domainHref": "https://www.miracles-of-quran.com/viscosity.html",
    "difficultyLevel": "मध्यम"
  },
  {
    "domainId": 146,
    "domainTitle": "हेलोकलाइन",
    "domainSubtitle": "जल स्तरीकरण।",
    "domainThumbnail": "images/domain_146.webp",
    "branchId": 8,
    "branchTitle": "रसायन शास्त्र",
    "branchSubtitle": "तत्वों और यौगिकों का विज्ञान",
    "branchThumbnail": "images/branch_8.webp",
    "branchHref": "https://www.miracles-of-quran.com/chemistry.html",
    "domainHref": "https://www.miracles-of-quran.com/halocline.html",
    "difficultyLevel": "चरम"
  },
  {
    "domainId": 147,
    "domainTitle": "रोशनी",
    "domainSubtitle": "पौधे अदृश्य प्रकाश उत्सर्जित करते हैं।",
    "domainThumbnail": "images/domain_147.webp",
    "branchId": 8,
    "branchTitle": "रसायन शास्त्र",
    "branchSubtitle": "तत्वों और यौगिकों का विज्ञान",
    "branchThumbnail": "images/branch_8.webp",
    "branchHref": "https://www.miracles-of-quran.com/chemistry.html",
    "domainHref": "https://www.miracles-of-quran.com/fluorescence.html",
    "difficultyLevel": "चरम"
  },
  {
    "domainId": 148,
    "domainTitle": "जंग",
    "domainSubtitle": "ऑक्सीकृत लोहा।",
    "domainThumbnail": "images/domain_148.webp",
    "branchId": 8,
    "branchTitle": "रसायन शास्त्र",
    "branchSubtitle": "तत्वों और यौगिकों का विज्ञान",
    "branchThumbnail": "images/branch_8.webp",
    "branchHref": "https://www.miracles-of-quran.com/chemistry.html",
    "domainHref": "https://www.miracles-of-quran.com/rust.html",
    "difficultyLevel": "मध्यम"
  },
  {
    "domainId": 149,
    "domainTitle": "सेल्सीयस",
    "domainSubtitle": "चाँदी का गलनांक।",
    "domainThumbnail": "images/domain_149.webp",
    "branchId": 8,
    "branchTitle": "रसायन शास्त्र",
    "branchSubtitle": "तत्वों और यौगिकों का विज्ञान",
    "branchThumbnail": "images/branch_8.webp",
    "branchHref": "https://www.miracles-of-quran.com/chemistry.html",
    "domainHref": "https://www.miracles-of-quran.com/celsius.html",
    "difficultyLevel": "आसान"
  },
  {
    "domainId": 150,
    "domainTitle": "क्लोरोफिल",
    "domainSubtitle": "हरा रंग और प्रकाश संश्लेषण।",
    "domainThumbnail": "images/domain_150.webp",
    "branchId": 9,
    "branchTitle": "वनस्पति विज्ञान",
    "branchSubtitle": "पौधों का विज्ञान",
    "branchThumbnail": "images/branch_9.webp",
    "branchHref": "https://www.miracles-of-quran.com/botany.html",
    "domainHref": "https://www.miracles-of-quran.com/photosynthesis.html",
    "difficultyLevel": "मध्यम"
  },
  {
    "domainId": 151,
    "domainTitle": "एंटीऑक्सीडेंट",
    "domainSubtitle": "हमारे शरीर की रक्षा करो।",
    "domainThumbnail": "images/domain_151.webp",
    "branchId": 9,
    "branchTitle": "वनस्पति विज्ञान",
    "branchSubtitle": "पौधों का विज्ञान",
    "branchThumbnail": "images/branch_9.webp",
    "branchHref": "https://www.miracles-of-quran.com/botany.html",
    "domainHref": "https://www.miracles-of-quran.com/antioxidants.html",
    "difficultyLevel": "मध्यम"
  },
  {
    "domainId": 152,
    "domainTitle": "परागन",
    "domainSubtitle": "हवा की भूमिका।",
    "domainThumbnail": "images/domain_152.webp",
    "branchId": 9,
    "branchTitle": "वनस्पति विज्ञान",
    "branchSubtitle": "पौधों का विज्ञान",
    "branchThumbnail": "images/branch_9.webp",
    "branchHref": "https://www.miracles-of-quran.com/botany.html",
    "domainHref": "https://www.miracles-of-quran.com/pollination.html",
    "difficultyLevel": "आसान"
  },
  {
    "domainId": 153,
    "domainTitle": "संयंत्र तनाव",
    "domainSubtitle": "पत्तियों को पीला कर देता है।",
    "domainThumbnail": "images/domain_153.webp",
    "branchId": 9,
    "branchTitle": "वनस्पति विज्ञान",
    "branchSubtitle": "पौधों का विज्ञान",
    "branchThumbnail": "images/branch_9.webp",
    "branchHref": "https://www.miracles-of-quran.com/botany.html",
    "domainHref": "https://www.miracles-of-quran.com/plant_stress.html",
    "difficultyLevel": "उन्नत"
  },
  {
    "domainId": 154,
    "domainTitle": "गार्डन",
    "domainSubtitle": "प्राकृतिक एंटीडिप्रेसेंट।",
    "domainThumbnail": "images/domain_154.webp",
    "branchId": 9,
    "branchTitle": "वनस्पति विज्ञान",
    "branchSubtitle": "पौधों का विज्ञान",
    "branchThumbnail": "images/branch_9.webp",
    "branchHref": "https://www.miracles-of-quran.com/botany.html",
    "domainHref": "https://www.miracles-of-quran.com/gardens.html",
    "difficultyLevel": "आसान"
  },
  {
    "domainId": 155,
    "domainTitle": "ठंढ",
    "domainSubtitle": "पौधों को मारता है।",
    "domainThumbnail": "images/domain_155.webp",
    "branchId": 9,
    "branchTitle": "वनस्पति विज्ञान",
    "branchSubtitle": "पौधों का विज्ञान",
    "branchThumbnail": "images/branch_9.webp",
    "branchHref": "https://www.miracles-of-quran.com/botany.html",
    "domainHref": "https://www.miracles-of-quran.com/frost.html",
    "difficultyLevel": "मध्यम"
  },
  {
    "domainId": 156,
    "domainTitle": "अंजीर",
    "domainSubtitle": "पालतू बनाना।",
    "domainThumbnail": "images/domain_156.webp",
    "branchId": 9,
    "branchTitle": "वनस्पति विज्ञान",
    "branchSubtitle": "पौधों का विज्ञान",
    "branchThumbnail": "images/branch_9.webp",
    "branchHref": "https://www.miracles-of-quran.com/botany.html",
    "domainHref": "https://www.miracles-of-quran.com/fig.html",
    "difficultyLevel": "आसान"
  },
  {
    "domainId": 157,
    "domainTitle": "भ्रूण विकास",
    "domainSubtitle": "चेहरे की विशेषताएं।",
    "domainThumbnail": "images/domain_157.webp",
    "branchId": 10,
    "branchTitle": "भ्रूणविज्ञान",
    "branchSubtitle": "प्रसवपूर्व विकास का विज्ञान",
    "branchThumbnail": "images/branch_10.webp",
    "branchHref": "https://www.miracles-of-quran.com/embryology.html",
    "domainHref": "https://www.miracles-of-quran.com/fetal_development.html",
    "difficultyLevel": "उन्नत"
  },
  {
    "domainId": 158,
    "domainTitle": "गर्भपात",
    "domainSubtitle": "तनाव से जुड़ा हुआ।",
    "domainThumbnail": "images/domain_158.webp",
    "branchId": 10,
    "branchTitle": "भ्रूणविज्ञान",
    "branchSubtitle": "प्रसवपूर्व विकास का विज्ञान",
    "branchThumbnail": "images/branch_10.webp",
    "branchHref": "https://www.miracles-of-quran.com/embryology.html",
    "domainHref": "https://www.miracles-of-quran.com/miscarriage.html",
    "difficultyLevel": "मध्यम"
  },
  {
    "domainId": 159,
    "domainTitle": "मानव भ्रूण",
    "domainSubtitle": "खिलाने के लिए माँ से जुड़ जाता है।",
    "domainThumbnail": "images/domain_159.webp",
    "branchId": 10,
    "branchTitle": "भ्रूणविज्ञान",
    "branchSubtitle": "प्रसवपूर्व विकास का विज्ञान",
    "branchThumbnail": "images/branch_10.webp",
    "branchHref": "https://www.miracles-of-quran.com/embryology.html",
    "domainHref": "https://www.miracles-of-quran.com/human_embryo.html",
    "difficultyLevel": "मध्यम"
  },
  {
    "domainId": 160,
    "domainTitle": "लिंग",
    "domainSubtitle": "गुणसूत्र।",
    "domainThumbnail": "images/domain_160.webp",
    "branchId": 10,
    "branchTitle": "भ्रूणविज्ञान",
    "branchSubtitle": "प्रसवपूर्व विकास का विज्ञान",
    "branchThumbnail": "images/branch_10.webp",
    "branchHref": "https://www.miracles-of-quran.com/embryology.html",
    "domainHref": "https://www.miracles-of-quran.com/gender.html",
    "difficultyLevel": "मध्यम"
  },
  {
    "domainId": 161,
    "domainTitle": "मानव इंद्रियां",
    "domainSubtitle": "दृष्टि से पहले श्रवण विकसित होता है।",
    "domainThumbnail": "images/domain_161.webp",
    "branchId": 10,
    "branchTitle": "भ्रूणविज्ञान",
    "branchSubtitle": "प्रसवपूर्व विकास का विज्ञान",
    "branchThumbnail": "images/branch_10.webp",
    "branchHref": "https://www.miracles-of-quran.com/embryology.html",
    "domainHref": "https://www.miracles-of-quran.com/human_senses.html",
    "difficultyLevel": "मध्यम"
  },
  {
    "domainId": 162,
    "domainTitle": "कोख",
    "domainSubtitle": "अस्तर मोटाई बदलता है।",
    "domainThumbnail": "images/domain_162.webp",
    "branchId": 10,
    "branchTitle": "भ्रूणविज्ञान",
    "branchSubtitle": "प्रसवपूर्व विकास का विज्ञान",
    "branchThumbnail": "images/branch_10.webp",
    "branchHref": "https://www.miracles-of-quran.com/embryology.html",
    "domainHref": "https://www.miracles-of-quran.com/womb.html",
    "difficultyLevel": "उन्नत"
  },
  {
    "domainId": 163,
    "domainTitle": "उल्बीय तरल पदार्थ",
    "domainSubtitle": "पानी और अंधेरे में भ्रूण.",
    "domainThumbnail": "images/domain_163.webp",
    "branchId": 10,
    "branchTitle": "भ्रूणविज्ञान",
    "branchSubtitle": "प्रसवपूर्व विकास का विज्ञान",
    "branchThumbnail": "images/branch_10.webp",
    "branchHref": "https://www.miracles-of-quran.com/embryology.html",
    "domainHref": "https://www.miracles-of-quran.com/amniotic_fluid.html",
    "difficultyLevel": "उन्नत"
  },
  {
    "domainId": 164,
    "domainTitle": "शुक्राणु",
    "domainSubtitle": "क्रोमोसोम अद्वितीय नहीं हैं।",
    "domainThumbnail": "images/domain_164.webp",
    "branchId": 10,
    "branchTitle": "भ्रूणविज्ञान",
    "branchSubtitle": "प्रसवपूर्व विकास का विज्ञान",
    "branchThumbnail": "images/branch_10.webp",
    "branchHref": "https://www.miracles-of-quran.com/embryology.html",
    "domainHref": "https://www.miracles-of-quran.com/sperm.html",
    "difficultyLevel": "मध्यम"
  },
  {
    "domainId": 165,
    "domainTitle": "अभाज्य सँख्या",
    "domainSubtitle": "अविभाज्य।",
    "domainThumbnail": "images/domain_165.webp",
    "branchId": 11,
    "branchTitle": "गणित",
    "branchSubtitle": "मात्रा, संरचना, स्थान और परिवर्तन का विज्ञान",
    "branchThumbnail": "images/branch_11.webp",
    "branchHref": "https://www.miracles-of-quran.com/mathematics.html",
    "domainHref": "https://www.miracles-of-quran.com/prime_numbers.html",
    "difficultyLevel": "आसान"
  },
  {
    "domainId": 166,
    "domainTitle": "दूरी",
    "domainSubtitle": "मीटर, किलोमीटर, मील, प्रकाश वर्ष।",
    "domainThumbnail": "images/domain_166.webp",
    "branchId": 11,
    "branchTitle": "गणित",
    "branchSubtitle": "मात्रा, संरचना, स्थान और परिवर्तन का विज्ञान",
    "branchThumbnail": "images/branch_11.webp",
    "branchHref": "https://www.miracles-of-quran.com/mathematics.html",
    "domainHref": "https://www.miracles-of-quran.com/distance.html",
    "difficultyLevel": "मध्यम"
  },
  {
    "domainId": 167,
    "domainTitle": "अनुकरणीय",
    "domainSubtitle": "पाई \u003d 3.14",
    "domainThumbnail": "images/domain_167.webp",
    "branchId": 11,
    "branchTitle": "गणित",
    "branchSubtitle": "मात्रा, संरचना, स्थान और परिवर्तन का विज्ञान",
    "branchThumbnail": "images/branch_11.webp",
    "branchHref": "https://www.miracles-of-quran.com/mathematics.html",
    "domainHref": "https://www.miracles-of-quran.com/pi.html",
    "difficultyLevel": "मध्यम"
  },
  {
    "domainId": 168,
    "domainTitle": "बेस -19",
    "domainSubtitle": "अंक प्रणाली।",
    "domainThumbnail": "images/domain_168.webp",
    "branchId": 11,
    "branchTitle": "गणित",
    "branchSubtitle": "मात्रा, संरचना, स्थान और परिवर्तन का विज्ञान",
    "branchThumbnail": "images/branch_11.webp",
    "branchHref": "https://www.miracles-of-quran.com/mathematics.html",
    "domainHref": "https://www.miracles-of-quran.com/base-19.html",
    "difficultyLevel": "मध्यम"
  },
  {
    "domainId": 170,
    "domainTitle": "एन्कोडिंग",
    "domainSubtitle": "अक्षरों को सांकेतिक अक्षरों में बदलना।",
    "domainThumbnail": "images/domain_170.webp",
    "branchId": 11,
    "branchTitle": "गणित",
    "branchSubtitle": "मात्रा, संरचना, स्थान और परिवर्तन का विज्ञान",
    "branchThumbnail": "images/branch_11.webp",
    "branchHref": "https://www.miracles-of-quran.com/mathematics.html",
    "domainHref": "https://www.miracles-of-quran.com/encoding.html",
    "difficultyLevel": "मध्यम"
  },
  {
    "domainId": 171,
    "domainTitle": "अजाद अंक",
    "domainSubtitle": "अल्फ़ान्यूमेरिक कोड।",
    "domainThumbnail": "images/domain_171.webp",
    "branchId": 11,
    "branchTitle": "गणित",
    "branchSubtitle": "मात्रा, संरचना, स्थान और परिवर्तन का विज्ञान",
    "branchThumbnail": "images/branch_11.webp",
    "branchHref": "https://www.miracles-of-quran.com/mathematics.html",
    "domainHref": "https://www.miracles-of-quran.com/abjad_numerals.html",
    "difficultyLevel": "मध्यम"
  },
  {
    "domainId": 172,
    "domainTitle": "ब्रह्मांड का आकार",
    "domainSubtitle": "अंतरिक्ष की वक्रता।",
    "domainThumbnail": "images/domain_172.webp",
    "branchId": 12,
    "branchTitle": "ब्रह्मांड विज्ञान",
    "branchSubtitle": "ब्रह्मांड की उत्पत्ति और विकास का विज्ञान",
    "branchThumbnail": "images/branch_12.webp",
    "branchHref": "https://www.miracles-of-quran.com/cosmology.html",
    "domainHref": "https://www.miracles-of-quran.com/shape_of_universe.html",
    "difficultyLevel": "चरम"
  },
  {
    "domainId": 173,
    "domainTitle": "सात स्वर्ग",
    "domainSubtitle": "अतिरिक्त आयामों में द्रव्यमान।",
    "domainThumbnail": "images/domain_173.webp",
    "branchId": 12,
    "branchTitle": "ब्रह्मांड विज्ञान",
    "branchSubtitle": "ब्रह्मांड की उत्पत्ति और विकास का विज्ञान",
    "branchThumbnail": "images/branch_12.webp",
    "branchHref": "https://www.miracles-of-quran.com/cosmology.html",
    "domainHref": "https://www.miracles-of-quran.com/seven_heavens.html",
    "difficultyLevel": "चरम"
  },
  {
    "domainId": 174,
    "domainTitle": "ब्रह्मांड की आयु",
    "domainSubtitle": "पृथ्वी की आयु ब्रह्मांड की 1/3 आयु।",
    "domainThumbnail": "images/domain_174.webp",
    "branchId": 12,
    "branchTitle": "ब्रह्मांड विज्ञान",
    "branchSubtitle": "ब्रह्मांड की उत्पत्ति और विकास का विज्ञान",
    "branchThumbnail": "images/branch_12.webp",
    "branchHref": "https://www.miracles-of-quran.com/cosmology.html",
    "domainHref": "https://www.miracles-of-quran.com/age_of_universe.html",
    "difficultyLevel": "चरम"
  },
  {
    "domainId": 175,
    "domainTitle": "विस्तार ब्रह्मांड",
    "domainSubtitle": "बिग बैंग के बाद से विस्तार।",
    "domainThumbnail": "images/domain_175.webp",
    "branchId": 12,
    "branchTitle": "ब्रह्मांड विज्ञान",
    "branchSubtitle": "ब्रह्मांड की उत्पत्ति और विकास का विज्ञान",
    "branchThumbnail": "images/branch_12.webp",
    "branchHref": "https://www.miracles-of-quran.com/cosmology.html",
    "domainHref": "https://www.miracles-of-quran.com/expanding_universe.html",
    "difficultyLevel": "चरम"
  },
  {
    "domainId": 176,
    "domainTitle": "महा विस्फोट",
    "domainSubtitle": "ब्रह्मांड का निर्माण।",
    "domainThumbnail": "images/domain_176.webp",
    "branchId": 12,
    "branchTitle": "ब्रह्मांड विज्ञान",
    "branchSubtitle": "ब्रह्मांड की उत्पत्ति और विकास का विज्ञान",
    "branchThumbnail": "images/branch_12.webp",
    "branchHref": "https://www.miracles-of-quran.com/cosmology.html",
    "domainHref": "https://www.miracles-of-quran.com/big_bang_crunch.html",
    "difficultyLevel": "चरम"
  },
  {
    "domainId": 177,
    "domainTitle": "ध्वनि तरंगे",
    "domainSubtitle": "ब्रह्मांड में सबसे पुरानी ध्वनि तरंगें।",
    "domainThumbnail": "images/domain_177.webp",
    "branchId": 12,
    "branchTitle": "ब्रह्मांड विज्ञान",
    "branchSubtitle": "ब्रह्मांड की उत्पत्ति और विकास का विज्ञान",
    "branchThumbnail": "images/branch_12.webp",
    "branchHref": "https://www.miracles-of-quran.com/cosmology.html",
    "domainHref": "https://www.miracles-of-quran.com/sound_waves.html",
    "difficultyLevel": "चरम"
  },
  {
    "domainId": 178,
    "domainTitle": "आइसोट्रॉपी",
    "domainSubtitle": "अंतरिक्ष में कोई पसंदीदा दिशा नहीं।",
    "domainThumbnail": "images/domain_178.webp",
    "branchId": 12,
    "branchTitle": "ब्रह्मांड विज्ञान",
    "branchSubtitle": "ब्रह्मांड की उत्पत्ति और विकास का विज्ञान",
    "branchThumbnail": "images/branch_12.webp",
    "branchHref": "https://www.miracles-of-quran.com/cosmology.html",
    "domainHref": "https://www.miracles-of-quran.com/isotropy.html",
    "difficultyLevel": "चरम"
  },
  {
    "domainId": 179,
    "domainTitle": "आदिम धुआँ",
    "domainSubtitle": "बिग बैंग के ठीक बाद।",
    "domainThumbnail": "images/domain_179.webp",
    "branchId": 12,
    "branchTitle": "ब्रह्मांड विज्ञान",
    "branchSubtitle": "ब्रह्मांड की उत्पत्ति और विकास का विज्ञान",
    "branchThumbnail": "images/branch_12.webp",
    "branchHref": "https://www.miracles-of-quran.com/cosmology.html",
    "domainHref": "https://www.miracles-of-quran.com/primordial_smoke.html",
    "difficultyLevel": "चरम"
  },
  {
    "domainId": 180,
    "domainTitle": "काली ऊर्जा",
    "domainSubtitle": "ब्रह्मांड के विस्तार का कारण बनता है।",
    "domainThumbnail": "images/domain_180.webp",
    "branchId": 12,
    "branchTitle": "ब्रह्मांड विज्ञान",
    "branchSubtitle": "ब्रह्मांड की उत्पत्ति और विकास का विज्ञान",
    "branchThumbnail": "images/branch_12.webp",
    "branchHref": "https://www.miracles-of-quran.com/cosmology.html",
    "domainHref": "https://www.miracles-of-quran.com/dark_energy.html",
    "difficultyLevel": "चरम"
  },
  {
    "domainId": 181,
    "domainTitle": "गैलेक्सी फिलामेंट्स",
    "domainSubtitle": "ब्रह्मांड में सबसे बड़ी ज्ञात संरचनाएं।",
    "domainThumbnail": "images/domain_181.webp",
    "branchId": 12,
    "branchTitle": "ब्रह्मांड विज्ञान",
    "branchSubtitle": "ब्रह्मांड की उत्पत्ति और विकास का विज्ञान",
    "branchThumbnail": "images/branch_12.webp",
    "branchHref": "https://www.miracles-of-quran.com/cosmology.html",
    "domainHref": "https://www.miracles-of-quran.com/galaxy_filaments.html",
    "difficultyLevel": "चरम"
  },
  {
    "domainId": 182,
    "domainTitle": "स्काइडाइविंग",
    "domainSubtitle": "आकाश से मुक्त-पतन।",
    "domainThumbnail": "images/domain_182.webp",
    "branchId": 4,
    "branchTitle": "इतिहास",
    "branchSubtitle": "अतीत का अध्ययन",
    "branchThumbnail": "images/branch_4.webp",
    "branchHref": "https://www.miracles-of-quran.com/history.html",
    "domainHref": "https://www.miracles-of-quran.com/skydiving.html",
    "difficultyLevel": "आसान"
  },
  {
    "domainId": 183,
    "domainTitle": "मस्तिष्क स्तंभ",
    "domainSubtitle": "नींद और मौत से जुड़ा हुआ।",
    "domainThumbnail": "images/domain_183.webp",
    "branchId": 15,
    "branchTitle": "शरीर क्रिया विज्ञान",
    "branchSubtitle": "अंगों के कार्य",
    "branchThumbnail": "images/branch_15.webp",
    "branchHref": "https://www.miracles-of-quran.com/physiology.html",
    "domainHref": "https://www.miracles-of-quran.com/brainstem.html",
    "difficultyLevel": "चरम"
  },
  {
    "domainId": 184,
    "domainTitle": "साष्टांग प्रणाम",
    "domainSubtitle": "ठोड़ी पर।",
    "domainThumbnail": "images/domain_184.jpeg",
    "branchId": 13,
    "branchTitle": "मिसरशास्र",
    "branchSubtitle": "प्राचीन मिस्र का अध्ययन",
    "branchThumbnail": "images/branch_13.webp",
    "branchHref": "https://www.miracles-of-quran.com/egyptology.html",
    "domainHref": "https://www.miracles-of-quran.com/prostrations.html",
    "difficultyLevel": "आसान"
  },
  {
    "domainId": 185,
    "domainTitle": "पोषक चक्र",
    "domainSubtitle": "विघटित पदार्थ का पुनर्चक्रण।",
    "domainThumbnail": "images/domain_185.webp",
    "branchId": 9,
    "branchTitle": "वनस्पति विज्ञान",
    "branchSubtitle": "पौधों का विज्ञान",
    "branchThumbnail": "images/branch_9.webp",
    "branchHref": "https://www.miracles-of-quran.com/botany.html",
    "domainHref": "https://www.miracles-of-quran.com/nutrient_cycle.html",
    "difficultyLevel": "आसान"
  },
  {
    "domainId": 186,
    "domainTitle": "मस्तिष्क की कोशिकाएं",
    "domainSubtitle": "दिल में मिला",
    "domainThumbnail": "images/domain_186.webp",
    "branchId": 15,
    "branchTitle": "शरीर क्रिया विज्ञान",
    "branchSubtitle": "अंगों के कार्य",
    "branchThumbnail": "images/branch_15.webp",
    "branchHref": "https://www.miracles-of-quran.com/physiology.html",
    "domainHref": "https://www.miracles-of-quran.com/brain_cells.html",
    "difficultyLevel": "चरम"
  },
  {
    "domainId": 187,
    "domainTitle": "पल्सर नेविगेशन",
    "domainSubtitle": "जीपीएस की जगह",
    "domainThumbnail": "images/domain_187.webp",
    "branchId": 11,
    "branchTitle": "गणित",
    "branchSubtitle": "मात्रा, संरचना, स्थान और परिवर्तन का विज्ञान",
    "branchThumbnail": "images/branch_11.webp",
    "branchHref": "https://www.miracles-of-quran.com/mathematics.html",
    "domainHref": "https://www.miracles-of-quran.com/pulsar_navigation.html",
    "difficultyLevel": "उन्नत"
  },
  {
    "domainId": 188,
    "domainTitle": "फ्लैश ब्लाइंडनेस",
    "domainSubtitle": "बिजली गिरने से जुड़ा हुआ है",
    "domainThumbnail": "images/domain_188.webp",
    "branchId": 15,
    "branchTitle": "शरीर क्रिया विज्ञान",
    "branchSubtitle": "अंगों के कार्य",
    "branchThumbnail": "images/branch_15.webp",
    "branchHref": "https://www.miracles-of-quran.com/physiology.html",
    "domainHref": "https://www.miracles-of-quran.com/flash_blindness.html",
    "difficultyLevel": "आसान"
  },
  {
    "domainId": 189,
    "domainTitle": "हाइड्रोजन पेरोक्साइड",
    "domainSubtitle": "सफेद बाल और कमजोर हड्डियों से जुड़ा हुआ।",
    "domainThumbnail": "images/domain_189.webp",
    "branchId": 8,
    "branchTitle": "रसायन शास्त्र",
    "branchSubtitle": "तत्वों और यौगिकों का विज्ञान",
    "branchThumbnail": "images/branch_8.webp",
    "branchHref": "https://www.miracles-of-quran.com/chemistry.html",
    "domainHref": "https://www.miracles-of-quran.com/hydrogen_peroxide.html",
    "difficultyLevel": "आसान"
  },
  {
    "domainId": 190,
    "domainTitle": "अक्षीय झुकाव",
    "domainSubtitle": "अदृश्य धनुष",
    "domainThumbnail": "images/domain_190.webp",
    "branchId": 5,
    "branchTitle": "खगोल",
    "branchSubtitle": "आकाशीय पिंडों का विज्ञान",
    "branchThumbnail": "images/branch_5.jpg",
    "branchHref": "https://www.miracles-of-quran.com/astronomy.html",
    "domainHref": "https://www.miracles-of-quran.com/axial_tilt.html",
    "difficultyLevel": "आसान"
  },
  {
    "domainId": 191,
    "domainTitle": "सौर ऊर्जा",
    "domainSubtitle": "ऊर्जा संरक्षण।",
    "domainThumbnail": "images/domain_191.webp",
    "branchId": 3,
    "branchTitle": "भौतिक विज्ञान",
    "branchSubtitle": "अंतरिक्ष और समय के माध्यम से गति और व्यवहार का विज्ञान",
    "branchThumbnail": "images/branch_3.webp",
    "branchHref": "https://www.miracles-of-quran.com/physics.html",
    "domainHref": "https://www.miracles-of-quran.com/solar_energy.html",
    "difficultyLevel": "आसान"
  },
  {
    "domainId": 192,
    "domainTitle": "बायोलुमिनसेंस",
    "domainSubtitle": "अपनी रोशनी खुद दो.",
    "domainThumbnail": "images/domain_192.webp",
    "branchId": 2,
    "branchTitle": "जीवविज्ञान",
    "branchSubtitle": "जीवों का विज्ञान",
    "branchThumbnail": "images/branch_2.jpeg",
    "branchHref": "https://www.miracles-of-quran.com/biology.html",
    "domainHref": "https://www.miracles-of-quran.com/bioluminescence.html",
    "difficultyLevel": "चरम"
  },
  {
    "domainId": 193,
    "domainTitle": "रंग की",
    "domainSubtitle": "मनुष्य मंद प्रकाश में रंग नहीं देख सकता।",
    "domainThumbnail": "images/domain_193.webp",
    "branchId": 2,
    "branchTitle": "जीवविज्ञान",
    "branchSubtitle": "जीवों का विज्ञान",
    "branchThumbnail": "images/branch_2.jpeg",
    "branchHref": "https://www.miracles-of-quran.com/biology.html",
    "domainHref": "https://www.miracles-of-quran.com/colors.html",
    "difficultyLevel": "आसान"
  },
  {
    "domainId": 194,
    "domainTitle": "ज्वारीय ताला",
    "domainSubtitle": "तारे का मुख सदैव एक ही पक्ष की ओर होता है।",
    "domainThumbnail": "images/domain_194.webp",
    "branchId": 5,
    "branchTitle": "खगोल",
    "branchSubtitle": "आकाशीय पिंडों का विज्ञान",
    "branchThumbnail": "images/branch_5.jpg",
    "branchHref": "https://www.miracles-of-quran.com/astronomy.html",
    "domainHref": "https://www.miracles-of-quran.com/tidal_locking.html",
    "difficultyLevel": "चरम"
  },
  {
    "domainId": 195,
    "domainTitle": "AMD",
    "domainSubtitle": "बुजुर्गों में धुंधली दृष्टि आयरन से जुड़ी हुई है।",
    "domainThumbnail": "images/domain_195.webp",
    "branchId": 15,
    "branchTitle": "शरीर क्रिया विज्ञान",
    "branchSubtitle": "अंगों के कार्य",
    "branchThumbnail": "images/branch_15.webp",
    "branchHref": "https://www.miracles-of-quran.com/physiology.html",
    "domainHref": "https://www.miracles-of-quran.com/amd.html",
    "difficultyLevel": "चरम"
  },
  {
    "domainId": 196,
    "domainTitle": "लाल विशाल",
    "domainSubtitle": "सूर्य पृथ्वी को निगल जाएगा।",
    "domainThumbnail": "images/domain_196.webp",
    "branchId": 5,
    "branchTitle": "खगोल",
    "branchSubtitle": "आकाशीय पिंडों का विज्ञान",
    "branchThumbnail": "images/branch_5.jpg",
    "branchHref": "https://www.miracles-of-quran.com/astronomy.html",
    "domainHref": "https://www.miracles-of-quran.com/red_giant.html",
    "difficultyLevel": "आसान"
  },
  {
    "domainId": 197,
    "domainTitle": "यूलर का नंबर",
    "domainSubtitle": "भगवान का सूत्र।",
    "domainThumbnail": "images/domain_197.webp",
    "branchId": 11,
    "branchTitle": "गणित",
    "branchSubtitle": "मात्रा, संरचना, स्थान और परिवर्तन का विज्ञान",
    "branchThumbnail": "images/branch_11.webp",
    "branchHref": "https://www.miracles-of-quran.com/mathematics.html",
    "domainHref": "https://www.miracles-of-quran.com/euler.html",
    "difficultyLevel": "उन्नत"
  },
  {
    "domainId": 198,
    "domainTitle": "सितारे",
    "domainSubtitle": "समय में पीछे मुड़कर देखें।",
    "domainThumbnail": "images/domain_198.webp",
    "branchId": 5,
    "branchTitle": "खगोल",
    "branchSubtitle": "आकाशीय पिंडों का विज्ञान",
    "branchThumbnail": "images/branch_5.jpg",
    "branchHref": "https://www.miracles-of-quran.com/astronomy.html",
    "domainHref": "https://www.miracles-of-quran.com/stars.html",
    "difficultyLevel": "आसान"
  },
  {
    "domainId": 199,
    "domainTitle": "सूखी नदी",
    "domainSubtitle": "पिरामिडों में नदियाँ थीं।",
    "domainThumbnail": "images/domain_199.webp",
    "branchId": 13,
    "branchTitle": "मिसरशास्र",
    "branchSubtitle": "प्राचीन मिस्र का अध्ययन",
    "branchThumbnail": "images/branch_13.webp",
    "branchHref": "https://www.miracles-of-quran.com/egyptology.html",
    "domainHref": "https://www.miracles-of-quran.com/dried_rivers.html",
    "difficultyLevel": "आसान"
  },
  {
    "domainId": 200,
    "domainTitle": "बड़ी कमी",
    "domainSubtitle": "गुरुत्वाकर्षण के कारण।",
    "domainThumbnail": "images/domain_200.gif",
    "branchId": 12,
    "branchTitle": "ब्रह्मांड विज्ञान",
    "branchSubtitle": "ब्रह्मांड की उत्पत्ति और विकास का विज्ञान",
    "branchThumbnail": "images/branch_12.webp",
    "branchHref": "https://www.miracles-of-quran.com/cosmology.html",
    "domainHref": "https://www.miracles-of-quran.com/big_crunch.html",
    "difficultyLevel": "चरम"
  }
]








