[{"section_type":"PARAGRAPH","content":"\u003cbr\u003e物理学では、重力に逆らう仕事は、単に重量に変位を掛けたものです。"},{"section_type":"GENERAL_REFERENCE","content":"他の力がない場合、重力はすべての自由に動く物体の一定の下向きの加速をもたらします。地球の表面近くでは、重力による加速度はg \u003d 9.8 ms-2であり、質量mの物体にかかる重力はFg\u003dmgです。この重力が物体の重心に集中していることを想像すると便利です。オブジェクトが垂直距離y2− y1で上向きまたは下向きに変位した場合、その重量mgによってオブジェクトに対して実行される仕事Wは次のようになります。\u003cbr\u003e W \u003d Fg（y2-y1）\u003dFgΔy\u003d-mgΔy\u003cbr\u003eここで、Fgは重量（インペリアル単位のポンド、SI単位のニュートン）であり、Δyは高さyの変化です。重力によって行われる作業は、オブジェクトの垂直方向の動きにのみ依存することに注意してください。摩擦の存在は、その重量によってオブジェクトに対して行われる作業に影響を与えません。","heading":"重力による仕事","reference_title":"ウィキペディア、仕事（物理学）、2019","reference_link":"https://en.wikipedia.org/wiki/Work_(physics)#Work_by_gravity"},{"section_type":"PARAGRAPH","content":"重力に逆らう仕事は、単に重量に変位を掛けたものです。これは最近知られていましたが、これは発見される1400年前のコーランで描写されていました。コーランでは、仕事は体重に関連しています。"},{"section_type":"QURAN_REFERENCE","content":"原子の重さの善の仕事をする人は誰でもそれを見るでしょう。そして、原子の重さの悪の働きをする人は誰でもそれを見るでしょう。","content_ar":"٧ فَمَنْ يَعْمَلْ مِثْقَالَ ذَرَّةٍ خَيْرًا يَرَهُ\u003cbr\u003e٨ وَمَنْ يَعْمَلْ مِثْقَالَ ذَرَّةٍ شَرًّا يَرَهُ","heading":"","reference_title":"コーラン99：7-8","reference_link":"https://www.quranwow.com/#/ch/99/t1/ar-allah/t2/en-itania/a1/alafasy-64/a2/itania-48-b/v/7"},{"section_type":"PARAGRAPH","content":"「Aamalعمل」は仕事を意味します。この節で「Yaamalيَعْمَلْ」は仕事をすることを意味します。ここで、作業（W）は重量（mg）にリンクされています。"},{"section_type":"MORAL","content":"1400年前に住んでいた非識字の男性は、体重が仕事に関係していることをどうやって知ることができたのでしょうか。"}]