[{"section_type":"PARAGRAPH","content":"لدينا جميعًا بصمات أصابع لكنها فريدة من نوعها ، حتى التوائم المتماثلة لها بصمات مختلفة. وقد عُرف هذا مؤخرًا ، إلا أن القرآن صوره قبل 1400 عام من اكتشافه ، ويذكر القرآن أنه في يوم القيامة يعيد الله خلق البشر بكل التفاصيل حتى أطراف أصابعهم. نحن نعلم اليوم أن أطراف الأصابع تلك تحتوي على بصمات فريدة لكل فرد."},{"section_type":"QURAN_REFERENCE","content":"نعم فعلا. نحن قادرون على إعادة بناء أطراف أصابعه.","content_ar":"٤ بَلَىٰ قَادِرِينَ عَلَىٰ أَنْ نُسَوِّيَ بَنَانَهُ","heading":"","reference_title":"القرآن 75: 4","reference_link":"https://www.quranwow.com/#/ch/75/t1/ar-allah/t2/en-itania/a1/alafasy-64/a2/none/v/4"},{"section_type":"PARAGRAPH","content":"في يوم القيامة يعيد الله بناء أجسادنا بأدق التفاصيل حتى بأطراف أصابعنا."},{"section_type":"MORAL","content":"كيف يمكن لرجل أمي عاش قبل 1400 عام أن يعرف أن أطراف الأصابع لديها شيء فريد؟"}]